{
  "dictionary" : {
    "ㄅㄧㄢˋ" : [
      "汴",
      "遍",
      "辨",
      "辯",
      "辮",
      "變",
      "便"
    ],
    "ㄅㄠ" : [
      "胞",
      "炮",
      "孢",
      "苞",
      "包",
      "褒",
      "煲"
    ],
    "ㄔㄨㄣˇ" : [
      "蠢"
    ],
    "ㄇㄧㄣˊ" : [
      "岷",
      "緡",
      "民"
    ],
    "ㄅㄢ" : [
      "搬",
      "斑",
      "般",
      "班",
      "頒"
    ],
    "ㄙˇ" : [
      "死"
    ],
    "ㄕㄡˇ" : [
      "守",
      "手",
      "首"
    ],
    "ㄉㄨㄢ" : [
      "端"
    ],
    "ㄅㄣ" : [
      "奔"
    ],
    "ㄖㄨㄛˋ" : [
      "篛",
      "箬",
      "若",
      "弱"
    ],
    "ㄅㄤ" : [
      "傍",
      "幫",
      "邦"
    ],
    "ㄅㄠˇ" : [
      "寶",
      "堡",
      "飽",
      "保",
      "葆",
      "褓"
    ],
    "ㄉㄨㄣ" : [
      "蹲",
      "墩",
      "敦"
    ],
    "ㄅㄥ" : [
      "崩",
      "繃"
    ],
    "ㄉㄜˊ" : [
      "德",
      "得"
    ],
    "ㄙˋ" : [
      "四",
      "巳",
      "肆",
      "嗣",
      "寺",
      "伺",
      "似",
      "飼",
      "祀",
      "賜",
      "駟",
      "耜",
      "姒"
    ],
    "ㄘㄨˋ" : [
      "卒",
      "蹙",
      "蹴",
      "醋",
      "促",
      "簇"
    ],
    "ㄅㄧ" : [
      "逼"
    ],
    "ㄕㄡˊ" : [
      "熟"
    ],
    "ㄉㄨㄥ" : [
      "鶇",
      "東",
      "冬",
      "鼕",
      "咚"
    ],
    "ㄎㄞˇ" : [
      "凱",
      "楷",
      "慨"
    ],
    "ㄕㄡˋ" : [
      "授",
      "獸",
      "壽",
      "售",
      "受",
      "瘦",
      "狩"
    ],
    "ㄅㄠˊ" : [
      "雹"
    ],
    "ㄇㄧㄝ" : [
      "咩"
    ],
    "ㄋㄨㄛˊ" : [
      "挪",
      "哪",
      "娜"
    ],
    "ㄧㄝˇ" : [
      "冶",
      "也",
      "野"
    ],
    "ㄉㄨㄣˇ" : [
      "盹"
    ],
    "ㄔㄨㄣˊ" : [
      "淳",
      "脣",
      "醇",
      "純",
      "鶉"
    ],
    "ㄅㄠˋ" : [
      "刨",
      "鮑",
      "報",
      "暴",
      "豹",
      "抱",
      "爆"
    ],
    "ㄋㄧㄥˊ" : [
      "嚀",
      "凝",
      "獰",
      "寧",
      "檸"
    ],
    "ㄊㄢˇ" : [
      "忐",
      "坦",
      "袒",
      "毯"
    ],
    "ㄋㄨㄛˋ" : [
      "糯",
      "諾",
      "懦"
    ],
    "ㄇㄧㄠ" : [
      "喵"
    ],
    "ㄇㄛˇ" : [
      "抹"
    ],
    "ㄧㄝˊ" : [
      "椰",
      "爺",
      "邪",
      "耶"
    ],
    "ㄋㄧㄥˋ" : [
      "濘"
    ],
    "ㄗㄨㄢ" : [
      "鑽"
    ],
    "ㄎㄞˋ" : [
      "愾"
    ],
    "ㄓㄠˇ" : [
      "爪",
      "沼",
      "找"
    ],
    "ㄗㄨㄣ" : [
      "遵",
      "鱒",
      "尊"
    ],
    "ㄧㄝˋ" : [
      "液",
      "頁",
      "夜",
      "腋",
      "業",
      "射",
      "咽",
      "靨",
      "葉"
    ],
    "ㄗㄜˊ" : [
      "嘖",
      "則",
      "澤",
      "責",
      "擇"
    ],
    "ㄊㄢˊ" : [
      "壇",
      "罈",
      "譚",
      "檀",
      "談",
      "彈",
      "痰",
      "潭"
    ],
    "ㄨㄚ" : [
      "挖",
      "蛙",
      "哇",
      "媧",
      "窪"
    ],
    "ㄨㄛ" : [
      "渦",
      "窩"
    ],
    "ㄊㄢˋ" : [
      "歎",
      "探",
      "碳",
      "嘆",
      "炭"
    ],
    "ㄇㄛˊ" : [
      "無",
      "麼",
      "模",
      "摩",
      "摹",
      "膜",
      "魔",
      "磨"
    ],
    "ㄗㄨㄥ" : [
      "縱",
      "棕",
      "蹤",
      "宗",
      "鬃"
    ],
    "ㄘㄨㄥˊ" : [
      "淙",
      "從",
      "叢"
    ],
    "ㄍㄨㄥˇ" : [
      "鞏",
      "拱"
    ],
    "ㄇㄛˋ" : [
      "末",
      "驀",
      "脈",
      "冒",
      "墨",
      "陌",
      "莫",
      "寞",
      "茉",
      "嘿",
      "磨",
      "默",
      "抹",
      "沒",
      "沫",
      "漠"
    ],
    "ㄓㄠˊ" : [
      "著"
    ],
    "ㄨㄞ" : [
      "歪"
    ],
    "ㄉㄨㄣˋ" : [
      "遁",
      "噸",
      "鈍",
      "燉",
      "沌",
      "盾",
      "頓"
    ],
    "ㄨㄣˇ" : [
      "刎",
      "穩",
      "吻"
    ],
    "ㄨㄟ" : [
      "逶",
      "偎",
      "萎",
      "威"
    ],
    "ㄓㄠˋ" : [
      "趙",
      "肇",
      "兆",
      "召",
      "罩",
      "照"
    ],
    "ㄘㄢˇ" : [
      "慘"
    ],
    "ㄋㄨˇ" : [
      "努",
      "弩"
    ],
    "ㄨㄢ" : [
      "灣",
      "蜿",
      "彎"
    ],
    "ㄏㄤˊ" : [
      "杭",
      "航",
      "行",
      "吭"
    ],
    "ㄨㄣ" : [
      "溫",
      "塭"
    ],
    "ㄤˊ" : [
      "昂"
    ],
    "ㄨㄤ" : [
      "汪"
    ],
    "ㄈㄡˇ" : [
      "否"
    ],
    "ㄨㄣˊ" : [
      "聞",
      "文",
      "蚊",
      "紋"
    ],
    "ㄤˋ" : [
      "盎"
    ],
    "ㄨㄥ" : [
      "翁",
      "嗡"
    ],
    "ㄌㄧㄢˇ" : [
      "臉"
    ],
    "ㄐㄧ" : [
      "雞",
      "跡",
      "犄",
      "期",
      "蹟",
      "奇",
      "肌",
      "几",
      "嘰",
      "姬",
      "激",
      "饑",
      "績",
      "積",
      "稽",
      "譏",
      "機",
      "飢",
      "磯",
      "基",
      "畸",
      "箕",
      "幾"
    ],
    "ㄊㄨㄛ" : [
      "託",
      "脫",
      "拖",
      "托"
    ],
    "ㄨㄣˋ" : [
      "文",
      "問",
      "紊"
    ],
    "ㄅㄚˇ" : [
      "靶",
      "把"
    ],
    "ㄘㄢˊ" : [
      "慚",
      "蠶",
      "殘"
    ],
    "ㄋㄨˊ" : [
      "奴"
    ],
    "ㄐㄩ" : [
      "据",
      "居",
      "沮",
      "拘"
    ],
    "ㄘㄢˋ" : [
      "璨",
      "燦"
    ],
    "ㄋㄨˋ" : [
      "怒"
    ],
    "ㄍㄨㄥˋ" : [
      "共",
      "貢",
      "供"
    ],
    "ㄓㄨㄟˋ" : [
      "惴",
      "墜",
      "綴",
      "贅"
    ],
    "ㄅㄚˊ" : [
      "拔",
      "跋"
    ],
    "ㄊㄨㄟ" : [
      "推"
    ],
    "ㄅㄚˋ" : [
      "罷",
      "霸",
      "伯",
      "把",
      "壩",
      "爸"
    ],
    "ㄌㄧㄢˊ" : [
      "聯",
      "連",
      "蓮",
      "廉",
      "憐",
      "漣",
      "鐮",
      "簾"
    ],
    "ㄐㄧㄤˇ" : [
      "蔣",
      "獎",
      "講",
      "槳"
    ],
    "ㄉㄧˇ" : [
      "柢",
      "抵",
      "牴",
      "底",
      "邸"
    ],
    "ㄊㄨㄢ" : [
      "湍"
    ],
    "ㄑㄩㄝˋ" : [
      "闕",
      "雀",
      "確",
      "怯",
      "卻",
      "鵲"
    ],
    "ㄌㄧㄢˋ" : [
      "斂",
      "鏈",
      "練",
      "殮",
      "鍊",
      "戀",
      "煉"
    ],
    "ㄘㄨㄛ" : [
      "蹉",
      "磋",
      "搓"
    ],
    "ㄓㄚˇ" : [
      "眨"
    ],
    "ㄆㄠˇ" : [
      "跑"
    ],
    "ㄊㄨㄣ" : [
      "吞"
    ],
    "ㄙㄨˊ" : [
      "俗"
    ],
    "ㄍㄣˋ" : [
      "亙"
    ],
    "ㄒㄧㄥˇ" : [
      "擤",
      "醒",
      "省"
    ],
    "ㄙㄨˋ" : [
      "速",
      "肅",
      "訴",
      "夙",
      "溯",
      "粟",
      "塑",
      "宿",
      "窣",
      "素"
    ],
    "ㄊㄜˋ" : [
      "忑",
      "特"
    ],
    "ㄖㄡˊ" : [
      "柔",
      "揉"
    ],
    "ㄉㄧˊ" : [
      "嘀",
      "笛",
      "滌",
      "迪",
      "敵",
      "的",
      "荻",
      "狄"
    ],
    "ㄗˇ" : [
      "仔",
      "籽",
      "子",
      "紫",
      "梓",
      "姊"
    ],
    "ㄊㄨㄥ" : [
      "通"
    ],
    "ㄎㄨㄢˇ" : [
      "款"
    ],
    "ㄏㄞˇ" : [
      "海"
    ],
    "ㄖㄡˋ" : [
      "肉"
    ],
    "ㄉㄧˋ" : [
      "地",
      "帝",
      "遞",
      "諦",
      "第",
      "的",
      "締",
      "弟",
      "蒂"
    ],
    "ㄓㄚˊ" : [
      "札",
      "閘",
      "紮",
      "鍘",
      "炸",
      "扎"
    ],
    "ㄆㄠˊ" : [
      "刨",
      "炮",
      "咆",
      "袍"
    ],
    "ㄘㄨㄟ" : [
      "摧",
      "崔",
      "催",
      "衰"
    ],
    "ㄓㄚˋ" : [
      "柵",
      "詐",
      "榨",
      "蚱",
      "吒",
      "炸",
      "乍"
    ],
    "ㄆㄠˋ" : [
      "砲",
      "泡",
      "炮",
      "皰"
    ],
    "ㄗˋ" : [
      "恣",
      "自",
      "字",
      "漬"
    ],
    "ㄙㄨㄢˋ" : [
      "算",
      "蒜"
    ],
    "ㄐㄧㄤˋ" : [
      "降",
      "醬",
      "將",
      "強",
      "匠"
    ],
    "ㄏㄞˊ" : [
      "骸",
      "孩",
      "還"
    ],
    "ㄏㄞˋ" : [
      "亥",
      "害",
      "駭"
    ],
    "ㄉㄧㄝˊ" : [
      "跌",
      "碟",
      "疊",
      "喋",
      "迭",
      "蝶"
    ],
    "ㄒㄧㄥˊ" : [
      "刑",
      "型",
      "形",
      "行"
    ],
    "ㄔㄠˇ" : [
      "炒",
      "吵"
    ],
    "ㄘㄨㄣ" : [
      "村"
    ],
    "ㄋㄢˊ" : [
      "南",
      "難",
      "楠",
      "喃",
      "男"
    ],
    "ㄒㄧㄥˋ" : [
      "興",
      "杏",
      "性",
      "倖",
      "行",
      "幸",
      "姓"
    ],
    "ㄘㄜˋ" : [
      "側",
      "冊",
      "策",
      "惻",
      "測",
      "廁"
    ],
    "ㄋㄢˋ" : [
      "難"
    ],
    "ㄈㄛˊ" : [
      "佛"
    ],
    "ㄘㄨㄥ" : [
      "聰",
      "囪",
      "匆",
      "蔥",
      "從",
      "樅"
    ],
    "ㄔㄠˊ" : [
      "朝",
      "潮",
      "嘲",
      "巢",
      "晁"
    ],
    "˙ㄌㄚ" : [
      "啦"
    ],
    "ㄎㄚ" : [
      "喀",
      "咖"
    ],
    "ㄩㄣˇ" : [
      "隕",
      "允"
    ],
    "˙ㄌㄛ" : [
      "咯"
    ],
    "ㄎㄜ" : [
      "柯",
      "棵",
      "磕",
      "軻",
      "蚵",
      "蝌",
      "苛",
      "瞌",
      "稞",
      "顆",
      "科"
    ],
    "ㄔㄨㄥˇ" : [
      "寵"
    ],
    "ㄇㄧㄥˊ" : [
      "冥",
      "銘",
      "鳴",
      "螟",
      "名",
      "明"
    ],
    "ㄙㄢˇ" : [
      "散",
      "傘"
    ],
    "ㄌㄨˇ" : [
      "擄",
      "虜",
      "滷",
      "魯",
      "櫓"
    ],
    "˙ㄌㄜ" : [
      "了"
    ],
    "ㄎㄞ" : [
      "開"
    ],
    "ㄐㄩㄢˇ" : [
      "捲",
      "卷"
    ],
    "ㄑㄧㄡˇ" : [
      "糗"
    ],
    "ㄉㄡˇ" : [
      "斗",
      "陡",
      "蚪",
      "抖"
    ],
    "ㄩㄣˊ" : [
      "云",
      "雲",
      "勻",
      "芸",
      "耘"
    ],
    "ㄇㄧㄥˋ" : [
      "命"
    ],
    "ㄎㄡ" : [
      "摳"
    ],
    "ㄍㄨㄞˇ" : [
      "拐",
      "枴"
    ],
    "ㄎㄢ" : [
      "刊",
      "堪",
      "看",
      "龕",
      "勘"
    ],
    "ㄩㄣˋ" : [
      "運",
      "熨",
      "韻",
      "孕",
      "醞",
      "蘊",
      "暈"
    ],
    "ㄢˇ" : [
      "俺"
    ],
    "ㄌㄨˊ" : [
      "廬",
      "蘆",
      "盧",
      "顱",
      "爐"
    ],
    "ㄎㄤ" : [
      "慷",
      "康"
    ],
    "ㄅㄥˇ" : [
      "繃"
    ],
    "ㄌㄨˋ" : [
      "麓",
      "鹿",
      "漉",
      "碌",
      "路",
      "陸",
      "鷺",
      "祿",
      "露",
      "賂",
      "錄"
    ],
    "ㄙㄢˋ" : [
      "散"
    ],
    "ㄎㄥ" : [
      "鏗",
      "吭",
      "坑"
    ],
    "ㄉㄨㄥˇ" : [
      "董",
      "懂"
    ],
    "ㄔㄨㄥˊ" : [
      "重",
      "崇",
      "蟲"
    ],
    "ㄢˋ" : [
      "案",
      "按",
      "岸",
      "暗",
      "黯"
    ],
    "ㄏㄨㄟˇ" : [
      "會",
      "毀",
      "悔"
    ],
    "ㄉㄡˋ" : [
      "逗",
      "鬥",
      "豆",
      "竇",
      "荳",
      "讀",
      "痘"
    ],
    "ㄆㄚˊ" : [
      "耙",
      "杷",
      "琶",
      "爬",
      "扒"
    ],
    "ㄎㄨ" : [
      "骷",
      "哭",
      "窟",
      "枯"
    ],
    "ㄎㄣˇ" : [
      "肯",
      "墾",
      "啃",
      "懇"
    ],
    "ㄑㄧㄡˊ" : [
      "求",
      "囚",
      "仇",
      "球",
      "毬"
    ],
    "ㄔㄨㄥˋ" : [
      "銃",
      "衝"
    ],
    "ㄆㄚˋ" : [
      "帕",
      "怕"
    ],
    "ㄧㄢˇ" : [
      "掩",
      "奄",
      "广",
      "眼",
      "儼",
      "鼴",
      "衍",
      "弇",
      "演"
    ],
    "ㄐㄩㄢˋ" : [
      "圈",
      "雋",
      "眷",
      "絹",
      "倦",
      "卷"
    ],
    "ㄅㄥˋ" : [
      "蹦",
      "繃",
      "迸"
    ],
    "ㄗㄡˇ" : [
      "走"
    ],
    "ㄊㄧˇ" : [
      "體"
    ],
    "ㄒㄩㄣˊ" : [
      "巡",
      "詢",
      "馴",
      "旬",
      "循",
      "尋"
    ],
    "ㄍㄨㄞˋ" : [
      "怪"
    ],
    "ㄙㄨㄛ" : [
      "蓑",
      "簑",
      "嗦",
      "縮",
      "娑",
      "莎",
      "梭"
    ],
    "ㄇㄠˇ" : [
      "卯"
    ],
    "ㄧㄢˊ" : [
      "妍",
      "鹽",
      "研",
      "嚴",
      "筵",
      "岩",
      "蜒",
      "巖",
      "顏",
      "沿",
      "延",
      "言",
      "閻",
      "炎",
      "簷"
    ],
    "ㄏㄨㄟˊ" : [
      "回",
      "洄",
      "迴"
    ],
    "ㄒㄩㄣˋ" : [
      "訓",
      "訊",
      "遜",
      "迅",
      "孫",
      "殉"
    ],
    "ㄧㄢˋ" : [
      "焰",
      "燕",
      "燄",
      "嚥",
      "雁",
      "驗",
      "諺",
      "堰",
      "豔",
      "彥",
      "厭",
      "咽",
      "宴",
      "晏",
      "硯"
    ],
    "ㄙㄚ" : [
      "撒"
    ],
    "ㄓㄥˇ" : [
      "整",
      "拯"
    ],
    "ㄙㄨㄛˇ" : [
      "瑣",
      "索",
      "鎖",
      "所"
    ],
    "ㄊㄧˊ" : [
      "蹄",
      "提",
      "啼",
      "題",
      "堤"
    ],
    "ㄉㄨㄥˋ" : [
      "凍",
      "洞",
      "棟",
      "動"
    ],
    "ㄏㄨㄟˋ" : [
      "蕙",
      "會",
      "誨",
      "惠",
      "諱",
      "繪",
      "喙",
      "穢",
      "彗",
      "彙",
      "慧",
      "賄",
      "卉",
      "晦",
      "匯"
    ],
    "ㄗㄡˋ" : [
      "揍",
      "驟",
      "奏"
    ],
    "ㄊㄧˋ" : [
      "涕",
      "剃",
      "嚏",
      "惕",
      "替",
      "屜"
    ],
    "ㄔㄚˊ" : [
      "查",
      "槎",
      "察",
      "茶"
    ],
    "ㄇㄠˊ" : [
      "毛",
      "髦",
      "矛",
      "茅",
      "錨"
    ],
    "ㄉㄧㄝ" : [
      "爹"
    ],
    "ㄐㄧㄝˇ" : [
      "解",
      "姐",
      "姊"
    ],
    "ㄙㄞ" : [
      "塞",
      "鰓",
      "腮"
    ],
    "ㄙㄨㄟ" : [
      "雖"
    ],
    "ㄔㄚˋ" : [
      "奼",
      "剎",
      "詫",
      "岔"
    ],
    "ㄇㄠˋ" : [
      "帽",
      "貌",
      "冒",
      "茂",
      "貿"
    ],
    "ㄙㄠ" : [
      "搔",
      "艘",
      "騷"
    ],
    "ㄕˇ" : [
      "矢",
      "屎",
      "史",
      "使",
      "駛",
      "始"
    ],
    "ㄌㄢˇ" : [
      "攬",
      "覽",
      "懶",
      "纜",
      "欖"
    ],
    "ㄓㄥˋ" : [
      "正",
      "掙",
      "鄭",
      "證",
      "政",
      "症"
    ],
    "ㄙㄡ" : [
      "颼",
      "嗖",
      "搜",
      "蒐"
    ],
    "ㄌㄧㄤˇ" : [
      "兩",
      "倆"
    ],
    "ㄙㄢ" : [
      "參",
      "三"
    ],
    "ㄉㄧㄠ" : [
      "刁",
      "雕",
      "凋",
      "叼",
      "貂",
      "鵰"
    ],
    "ㄙㄣ" : [
      "森"
    ],
    "ㄕˊ" : [
      "實",
      "石",
      "蝕",
      "食",
      "什",
      "十",
      "時",
      "拾"
    ],
    "ㄙㄤ" : [
      "桑",
      "喪"
    ],
    "ㄙㄨㄢ" : [
      "酸",
      "痠"
    ],
    "ㄉㄧㄡ" : [
      "丟"
    ],
    "ㄕˋ" : [
      "事",
      "柿",
      "市",
      "逝",
      "視",
      "仕",
      "釋",
      "軾",
      "試",
      "適",
      "噬",
      "誓",
      "士",
      "嗜",
      "世",
      "舐",
      "恃",
      "室",
      "識",
      "飾",
      "式",
      "侍",
      "示",
      "是",
      "拭",
      "勢",
      "氏"
    ],
    "ㄙㄥ" : [
      "僧"
    ],
    "ㄕㄠˇ" : [
      "少"
    ],
    "ㄙㄨㄣ" : [
      "孫",
      "飧"
    ],
    "ㄩㄝˋ" : [
      "躍",
      "月",
      "樂",
      "悅",
      "說",
      "嶽",
      "粵",
      "岳",
      "閱",
      "越"
    ],
    "ㄌㄢˊ" : [
      "闌",
      "嵐",
      "蘭",
      "瀾",
      "攔",
      "欄",
      "藍",
      "婪",
      "籃",
      "斕"
    ],
    "ㄉㄧㄢ" : [
      "癲",
      "巔",
      "顛"
    ],
    "ㄅㄧㄝˇ" : [
      "癟"
    ],
    "ㄐㄧㄝˊ" : [
      "劫",
      "杰",
      "竭",
      "桔",
      "捷",
      "睫",
      "節",
      "結",
      "櫛",
      "傑",
      "癤",
      "拮",
      "潔",
      "截",
      "頡"
    ],
    "ㄅㄟˇ" : [
      "北"
    ],
    "ㄌㄢˋ" : [
      "爛",
      "濫"
    ],
    "ㄙㄨ" : [
      "蘇",
      "酥",
      "穌",
      "甦"
    ],
    "ㄙㄜˋ" : [
      "圾",
      "澀",
      "瑟",
      "嗇",
      "塞",
      "色"
    ],
    "ㄙㄨㄥ" : [
      "松",
      "嵩",
      "忪",
      "鬆"
    ],
    "ㄕㄠˊ" : [
      "韶",
      "勺"
    ],
    "ㄐㄧㄝˋ" : [
      "介",
      "解",
      "誡",
      "藉",
      "屆",
      "芥",
      "借",
      "界",
      "戒"
    ],
    "ㄉㄧㄥ" : [
      "仃",
      "釘",
      "丁",
      "叮",
      "町",
      "盯"
    ],
    "ㄌㄧㄤˊ" : [
      "糧",
      "量",
      "粱",
      "良",
      "涼",
      "梁"
    ],
    "ㄕㄠˋ" : [
      "劭",
      "少",
      "哨",
      "召",
      "紹",
      "邵"
    ],
    "ㄍㄨˇ" : [
      "骨",
      "詁",
      "鼓",
      "滑",
      "穀",
      "谷",
      "古",
      "股",
      "賈"
    ],
    "ㄅㄟˋ" : [
      "焙",
      "蓓",
      "貝",
      "背",
      "悖",
      "輩",
      "倍",
      "憊",
      "被",
      "備",
      "狽"
    ],
    "ㄌㄧㄤˋ" : [
      "亮",
      "量",
      "輛",
      "諒",
      "涼",
      "晾"
    ],
    "ㄌㄚ" : [
      "啦",
      "拉"
    ],
    "ㄅㄧㄝˊ" : [
      "別"
    ],
    "ㄎㄨㄛˋ" : [
      "闊",
      "廓",
      "擴"
    ],
    "ㄗㄨㄣˋ" : [
      "圳"
    ],
    "ㄌㄨㄛ" : [
      "囉"
    ],
    "ㄇㄚˇ" : [
      "瑪",
      "碼",
      "嗎",
      "螞",
      "馬"
    ],
    "ㄊㄨㄢˊ" : [
      "團",
      "糰"
    ],
    "ㄍㄨˊ" : [
      "骨"
    ],
    "ㄅㄧㄝˋ" : [
      "彆"
    ],
    "ㄌㄟ" : [
      "勒"
    ],
    "ㄔㄨㄞˇ" : [
      "揣"
    ],
    "ㄆㄥˇ" : [
      "捧"
    ],
    "ㄍㄨˋ" : [
      "固",
      "雇",
      "鯝",
      "僱",
      "故",
      "估",
      "顧",
      "錮"
    ],
    "ㄊㄡˊ" : [
      "投",
      "頭"
    ],
    "ㄌㄠ" : [
      "撈"
    ],
    "ㄋㄧㄠˇ" : [
      "鳥"
    ],
    "ㄊㄡˋ" : [
      "透"
    ],
    "ㄇㄚˊ" : [
      "麻",
      "麼",
      "嘛",
      "蟆",
      "痲"
    ],
    "ㄑㄧㄚˇ" : [
      "卡"
    ],
    "ㄠˇ" : [
      "襖"
    ],
    "ㄌㄨㄣˊ" : [
      "圇",
      "掄",
      "輪",
      "論",
      "崙",
      "倫",
      "綸",
      "淪"
    ],
    "ㄏㄣˇ" : [
      "很",
      "狠"
    ],
    "ㄇㄚˋ" : [
      "罵",
      "螞"
    ],
    "ㄆㄥˊ" : [
      "蓬",
      "朋",
      "棚",
      "膨",
      "篷",
      "澎",
      "彭",
      "鵬",
      "硼"
    ],
    "ㄖㄨㄟˇ" : [
      "蕊"
    ],
    "ㄨㄢˇ" : [
      "挽",
      "碗",
      "輓",
      "浣",
      "宛",
      "婉",
      "晚"
    ],
    "ㄠˊ" : [
      "熬",
      "翱",
      "遨",
      "敖",
      "螯"
    ],
    "ㄆㄥˋ" : [
      "碰"
    ],
    "ㄠˋ" : [
      "奧",
      "懊",
      "傲",
      "澳"
    ],
    "ㄌㄨㄣˋ" : [
      "論"
    ],
    "˙ㄨㄚ" : [
      "哇"
    ],
    "ㄌㄧ" : [
      "哩"
    ],
    "ㄌㄨ" : [
      "嚕"
    ],
    "ㄋㄧˇ" : [
      "妳",
      "擬",
      "你"
    ],
    "ㄎㄨㄤˊ" : [
      "狂"
    ],
    "ㄏㄣˊ" : [
      "痕"
    ],
    "ㄕㄚˇ" : [
      "傻"
    ],
    "ㄨㄢˊ" : [
      "頑",
      "烷",
      "完",
      "玩",
      "丸"
    ],
    "ㄏㄣˋ" : [
      "恨"
    ],
    "ㄌㄨㄣ" : [
      "掄"
    ],
    "ㄎㄨㄤˋ" : [
      "曠",
      "礦",
      "況"
    ],
    "ㄔㄥˇ" : [
      "逞",
      "騁"
    ],
    "ㄨㄢˋ" : [
      "腕",
      "惋",
      "萬"
    ],
    "ㄌㄜˋ" : [
      "樂",
      "肋",
      "垃",
      "勒"
    ],
    "ㄋㄧˊ" : [
      "妮",
      "尼",
      "霓",
      "倪",
      "呢",
      "泥"
    ],
    "ㄋㄧㄠˋ" : [
      "溺",
      "尿"
    ],
    "ㄘㄡˋ" : [
      "湊"
    ],
    "ㄋㄧˋ" : [
      "逆",
      "暱",
      "溺",
      "膩",
      "泥",
      "匿"
    ],
    "ㄊㄧㄝ" : [
      "帖",
      "貼"
    ],
    "ㄑㄧㄚˋ" : [
      "洽",
      "恰"
    ],
    "ㄐㄩˇ" : [
      "莒",
      "舉",
      "矩",
      "櫸",
      "咀",
      "沮"
    ],
    "ㄕㄚˋ" : [
      "霎",
      "殺",
      "煞"
    ],
    "ㄔㄥˊ" : [
      "誠",
      "成",
      "懲",
      "程",
      "橙",
      "城",
      "埕",
      "乘",
      "呈",
      "盛",
      "丞",
      "澄",
      "承"
    ],
    "ㄑㄧㄣˇ" : [
      "寢"
    ],
    "ㄖㄨㄟˋ" : [
      "銳",
      "瑞"
    ],
    "ㄍㄢˇ" : [
      "桿",
      "橄",
      "敢",
      "感",
      "稈",
      "趕"
    ],
    "ㄔㄥˋ" : [
      "秤",
      "稱"
    ],
    "ㄊㄧㄠ" : [
      "挑"
    ],
    "ㄓㄨㄚˇ" : [
      "爪"
    ],
    "ㄗㄞ" : [
      "災",
      "哉",
      "栽"
    ],
    "ㄐㄩˊ" : [
      "掬",
      "桔",
      "橘",
      "鞠",
      "局",
      "菊"
    ],
    "˙ㄕ" : [
      "匙"
    ],
    "ㄖㄠˇ" : [
      "擾"
    ],
    "ㄗㄠ" : [
      "糟",
      "遭",
      "蹧"
    ],
    "ㄐㄩˋ" : [
      "劇",
      "聚",
      "踞",
      "距",
      "巨",
      "據",
      "遽",
      "鋸",
      "炬",
      "具",
      "懼",
      "瞿",
      "鉅",
      "句",
      "俱",
      "拒"
    ],
    "ㄓˇ" : [
      "止",
      "指",
      "徵",
      "只",
      "紙",
      "祇",
      "祉",
      "旨",
      "咫",
      "趾",
      "枳",
      "址"
    ],
    "ㄊㄧㄢ" : [
      "添",
      "天"
    ],
    "˙ㄗ" : [
      "子"
    ],
    "ㄗㄡ" : [
      "鄒"
    ],
    "ㄍㄢˋ" : [
      "幹"
    ],
    "ㄓˊ" : [
      "擲",
      "職",
      "植",
      "值",
      "質",
      "蟄",
      "殖",
      "執",
      "直",
      "姪"
    ],
    "ㄗㄤ" : [
      "髒",
      "贓"
    ],
    "˙ㄚ" : [
      "啊"
    ],
    "ㄑㄧㄣˊ" : [
      "擒",
      "琴",
      "秦",
      "芹",
      "勤",
      "禽"
    ],
    "ㄆㄧㄣˇ" : [
      "品"
    ],
    "ㄓˋ" : [
      "置",
      "制",
      "誌",
      "摯",
      "峙",
      "幟",
      "滯",
      "致",
      "至",
      "炙",
      "識",
      "志",
      "稚",
      "質",
      "緻",
      "窒",
      "治",
      "智",
      "秩",
      "製"
    ],
    "ㄗㄥ" : [
      "增",
      "憎",
      "曾"
    ],
    "ㄖㄠˊ" : [
      "饒",
      "蟯"
    ],
    "ㄊㄧㄥ" : [
      "汀",
      "聽",
      "廳"
    ],
    "ㄖㄠˋ" : [
      "繞"
    ],
    "ㄑㄧㄣˋ" : [
      "沁"
    ],
    "ㄗㄨ" : [
      "租"
    ],
    "ㄆㄟˊ" : [
      "陪",
      "賠",
      "培",
      "坏",
      "邳"
    ],
    "ㄎㄨˇ" : [
      "苦"
    ],
    "ㄒㄩㄥˊ" : [
      "雄",
      "熊"
    ],
    "ㄆㄟˋ" : [
      "配",
      "珮",
      "佩",
      "沛"
    ],
    "ㄍㄨㄚ" : [
      "聒",
      "刮",
      "颳",
      "瓜",
      "蝸",
      "呱",
      "括"
    ],
    "ㄊㄨㄛˇ" : [
      "妥",
      "橢"
    ],
    "˙ㄣ" : [
      "嗯"
    ],
    "ㄓㄨㄣˇ" : [
      "准",
      "準"
    ],
    "ㄍㄨㄛ" : [
      "渦",
      "鍋",
      "郭"
    ],
    "ㄈㄚˇ" : [
      "砝",
      "髮",
      "法"
    ],
    "ㄆㄧㄣˊ" : [
      "貧",
      "頻"
    ],
    "ㄊㄧㄥˇ" : [
      "挺",
      "艇"
    ],
    "ㄇㄥˇ" : [
      "猛",
      "蜢",
      "錳",
      "艋"
    ],
    "ㄎㄨˋ" : [
      "酷",
      "褲",
      "庫"
    ],
    "ㄊㄚ" : [
      "她",
      "他",
      "塌",
      "它",
      "祂",
      "牠"
    ],
    "ㄕㄨㄛˋ" : [
      "朔",
      "碩",
      "數",
      "爍"
    ],
    "ㄍㄨㄞ" : [
      "乖"
    ],
    "ㄕㄨㄤˇ" : [
      "爽"
    ],
    "ㄌㄧㄝˋ" : [
      "列",
      "劣",
      "捩",
      "冽",
      "烈",
      "獵",
      "裂"
    ],
    "ㄈㄚˊ" : [
      "罰",
      "筏",
      "法",
      "乏"
    ],
    "ㄍㄨㄟ" : [
      "歸",
      "圭",
      "規",
      "閨",
      "瑰",
      "鮭",
      "龜"
    ],
    "ㄊㄞ" : [
      "胎"
    ],
    "˙ㄋㄚ" : [
      "哪"
    ],
    "ㄇㄥˊ" : [
      "矇",
      "濛",
      "朦",
      "萌",
      "懵",
      "檬",
      "盟",
      "蒙"
    ],
    "ㄒㄧㄠˇ" : [
      "小",
      "曉"
    ],
    "ㄩㄢˇ" : [
      "遠"
    ],
    "ㄊㄠ" : [
      "掏",
      "滔",
      "絛",
      "叨"
    ],
    "ㄍㄜˇ" : [
      "個",
      "合",
      "各",
      "葛"
    ],
    "ㄇㄥˋ" : [
      "夢",
      "孟"
    ],
    "ㄊㄨㄛˊ" : [
      "鴕",
      "跎",
      "陀",
      "佗",
      "沱",
      "駝",
      "馱"
    ],
    "ㄊㄡ" : [
      "偷"
    ],
    "ㄗㄨㄥˇ" : [
      "總"
    ],
    "ㄊㄢ" : [
      "癱",
      "攤",
      "灘",
      "貪"
    ],
    "ㄙㄡˇ" : [
      "擻",
      "叟"
    ],
    "˙ㄋㄜ" : [
      "呢"
    ],
    "ㄌㄧˇ" : [
      "里",
      "李",
      "理",
      "鯉",
      "裡",
      "哩",
      "豊",
      "禮",
      "邐"
    ],
    "ㄞˇ" : [
      "矮",
      "藹",
      "欸"
    ],
    "ㄊㄧㄥˊ" : [
      "亭",
      "蜓",
      "停",
      "霆",
      "婷",
      "廷",
      "庭"
    ],
    "ㄍㄨㄢ" : [
      "關",
      "棺",
      "觀",
      "冠",
      "官",
      "倌",
      "綸"
    ],
    "ㄊㄨㄛˋ" : [
      "魄",
      "唾",
      "拓"
    ],
    "ㄊㄤ" : [
      "湯"
    ],
    "ㄉㄠˇ" : [
      "擣",
      "搗",
      "島",
      "導",
      "倒",
      "禱"
    ],
    "ㄩㄢˊ" : [
      "園",
      "圓",
      "援",
      "轅",
      "源",
      "元",
      "猿",
      "湲",
      "員",
      "原",
      "緣",
      "袁",
      "垣"
    ],
    "ㄞˊ" : [
      "捱",
      "癌",
      "皚"
    ],
    "ㄍㄜˊ" : [
      "格",
      "骼",
      "閤",
      "閣",
      "隔",
      "蛤",
      "革",
      "葛"
    ],
    "ㄞˋ" : [
      "艾",
      "愛",
      "礙"
    ],
    "ㄊㄧㄥˋ" : [
      "聽"
    ],
    "ㄍㄨㄤ" : [
      "胱",
      "光"
    ],
    "ㄕㄥˇ" : [
      "省"
    ],
    "ㄩㄢˋ" : [
      "遠",
      "怨",
      "院",
      "苑",
      "願"
    ],
    "ㄍㄜˋ" : [
      "個",
      "各"
    ],
    "ㄊㄧ" : [
      "踢",
      "剔",
      "梯"
    ],
    "ㄌㄧˊ" : [
      "釐",
      "罹",
      "鸝",
      "離",
      "驪",
      "麗",
      "璃",
      "犁",
      "厘",
      "漓",
      "籬",
      "梨",
      "狸",
      "黎"
    ],
    "ㄊㄨ" : [
      "禿"
    ],
    "ㄍㄨㄥ" : [
      "功",
      "工",
      "躬",
      "蚣",
      "公",
      "恭",
      "宮",
      "攻",
      "紅",
      "供",
      "弓"
    ],
    "ㄇㄧㄠˇ" : [
      "眇",
      "渺",
      "秒"
    ],
    "ㄅㄤˇ" : [
      "榜",
      "膀",
      "綁"
    ],
    "ㄙㄡˋ" : [
      "嗽"
    ],
    "ㄌㄧˋ" : [
      "力",
      "栗",
      "利",
      "麗",
      "隸",
      "瀝",
      "笠",
      "厲",
      "粒",
      "戾",
      "靂",
      "苙",
      "立",
      "慄",
      "例",
      "曆",
      "俐",
      "礫",
      "蠣",
      "莉",
      "吏",
      "歷",
      "勵",
      "痢"
    ],
    "ㄋㄧㄝ" : [
      "捏"
    ],
    "ㄑㄩˇ" : [
      "取",
      "曲",
      "娶"
    ],
    "ㄌㄨㄥˇ" : [
      "隴",
      "壟",
      "攏"
    ],
    "ㄉㄠˋ" : [
      "到",
      "悼",
      "道",
      "蹈",
      "稻",
      "倒",
      "盜"
    ],
    "ㄕㄥˊ" : [
      "繩"
    ],
    "ㄒㄧㄠˋ" : [
      "嘯",
      "校",
      "酵",
      "肖",
      "笑",
      "孝",
      "效"
    ],
    "ㄎㄢˇ" : [
      "砍",
      "嵌",
      "崁",
      "檻",
      "侃",
      "坎"
    ],
    "ㄕㄥˋ" : [
      "聖",
      "剩",
      "乘",
      "盛",
      "勝"
    ],
    "ㄗㄨㄥˋ" : [
      "縱",
      "粽",
      "從",
      "綜"
    ],
    "ㄧㄡˇ" : [
      "有",
      "友",
      "酉",
      "黝"
    ],
    "ㄅㄤˋ" : [
      "棒",
      "磅",
      "蚌",
      "傍"
    ],
    "ㄑㄩˊ" : [
      "渠",
      "瞿",
      "麴"
    ],
    "ㄋㄧㄡ" : [
      "妞"
    ],
    "ㄕㄚ" : [
      "鯊",
      "砂",
      "紗",
      "殺",
      "沙",
      "莎",
      "煞"
    ],
    "ㄗㄠˇ" : [
      "棗",
      "藻",
      "蚤",
      "早",
      "澡"
    ],
    "ㄑㄩˋ" : [
      "覷",
      "去",
      "趣"
    ],
    "ㄐㄩㄝ" : [
      "撅"
    ],
    "ㄇㄧㄠˊ" : [
      "描",
      "苗",
      "瞄"
    ],
    "ㄕㄜ" : [
      "奢"
    ],
    "ㄋㄧㄢˇ" : [
      "碾",
      "輾",
      "拈"
    ],
    "ㄇㄟˇ" : [
      "美",
      "每"
    ],
    "ㄎㄢˋ" : [
      "看",
      "瞰"
    ],
    "ㄧㄡˊ" : [
      "疣",
      "遊",
      "魷",
      "游",
      "猶",
      "尤",
      "油",
      "郵",
      "由"
    ],
    "ㄕㄞ" : [
      "篩"
    ],
    "ㄌㄨㄥˊ" : [
      "聾",
      "朧",
      "嚨",
      "瓏",
      "隆",
      "龍",
      "窿",
      "籠"
    ],
    "ㄓㄤˇ" : [
      "掌",
      "長",
      "漲"
    ],
    "ㄇㄧㄠˋ" : [
      "妙",
      "繆",
      "廟"
    ],
    "ㄧㄡˋ" : [
      "柚",
      "有",
      "釉",
      "祐",
      "鈾",
      "誘",
      "右",
      "佑",
      "又",
      "幼"
    ],
    "ㄗㄠˊ" : [
      "鑿"
    ],
    "ㄕㄠ" : [
      "燒",
      "稍",
      "梢"
    ],
    "ㄕㄡ" : [
      "收"
    ],
    "ㄗㄠˋ" : [
      "造",
      "燥",
      "噪",
      "灶",
      "躁",
      "皂"
    ],
    "ㄌㄨㄥˋ" : [
      "弄"
    ],
    "ㄕㄢ" : [
      "跚",
      "杉",
      "刪",
      "搧",
      "山",
      "珊",
      "衫",
      "扇",
      "姍",
      "煽"
    ],
    "ㄇㄟˊ" : [
      "霉",
      "黴",
      "楣",
      "眉",
      "媒",
      "玫",
      "沒",
      "莓",
      "梅",
      "枚",
      "煤"
    ],
    "˙ㄅㄚ" : [
      "罷",
      "吧"
    ],
    "ㄩˇ" : [
      "予",
      "嶼",
      "雨",
      "噢",
      "羽",
      "與",
      "宇",
      "禹",
      "語"
    ],
    "ㄕㄣ" : [
      "身",
      "深",
      "申",
      "伸",
      "參",
      "紳",
      "呻"
    ],
    "ㄏㄨˇ" : [
      "琥",
      "虎",
      "滸",
      "唬"
    ],
    "ㄇㄟˋ" : [
      "妹",
      "寐",
      "魅",
      "媚",
      "昧"
    ],
    "ㄐㄩㄢ" : [
      "娟",
      "捐",
      "涓",
      "鵑"
    ],
    "ㄕㄤ" : [
      "商",
      "傷"
    ],
    "ㄕㄥ" : [
      "牲",
      "聲",
      "笙",
      "升",
      "昇",
      "甥",
      "生",
      "勝"
    ],
    "ㄩˊ" : [
      "予",
      "于",
      "萸",
      "逾",
      "瑜",
      "餘",
      "榆",
      "隅",
      "輿",
      "虞",
      "諛",
      "於",
      "魚",
      "渝",
      "漁",
      "愉",
      "愚",
      "余",
      "盂",
      "娛"
    ],
    "ㄎㄨㄚ" : [
      "夸",
      "誇"
    ],
    "ㄐㄩㄣ" : [
      "軍",
      "龜",
      "鈞",
      "均",
      "君"
    ],
    "ㄌㄡˇ" : [
      "摟",
      "簍"
    ],
    "ㄓㄤˋ" : [
      "帳",
      "仗",
      "杖",
      "脹",
      "障",
      "賬",
      "漲",
      "丈"
    ],
    "ㄩˋ" : [
      "遇",
      "燠",
      "雨",
      "熨",
      "鬻",
      "浴",
      "獄",
      "與",
      "峪",
      "寓",
      "喻",
      "譽",
      "芋",
      "鬱",
      "谷",
      "御",
      "尉",
      "愈",
      "豫",
      "育",
      "慾",
      "癒",
      "嫗",
      "諭",
      "玉",
      "域",
      "籲",
      "鷸",
      "預",
      "郁",
      "禦",
      "裕",
      "昱",
      "欲",
      "馭"
    ],
    "ㄐㄩㄝˊ" : [
      "決",
      "掘",
      "覺",
      "訣",
      "蕨",
      "嚼",
      "角",
      "倔",
      "崛",
      "獗",
      "絕",
      "橛",
      "抉",
      "爵"
    ],
    "ㄋㄧㄢˊ" : [
      "粘",
      "拈",
      "黏",
      "年"
    ],
    "ㄕㄨ" : [
      "疏",
      "樞",
      "輸",
      "舒",
      "蔬",
      "紓",
      "荼",
      "書",
      "殊",
      "抒",
      "梳"
    ],
    "ㄉㄚˇ" : [
      "打"
    ],
    "ㄏㄨˊ" : [
      "糊",
      "囫",
      "瑚",
      "胡",
      "壺",
      "斛",
      "蝴",
      "鬍",
      "湖",
      "和",
      "弧",
      "葫",
      "狐"
    ],
    "ㄐㄩㄝˋ" : [
      "倔"
    ],
    "ㄋㄧㄢˋ" : [
      "念",
      "唸",
      "廿"
    ],
    "ㄏㄨˋ" : [
      "互",
      "瓠",
      "滬",
      "護",
      "扈",
      "戶"
    ],
    "ㄌㄡˊ" : [
      "嘍",
      "髏",
      "樓"
    ],
    "ㄅㄞˇ" : [
      "襬",
      "擺",
      "佰",
      "百"
    ],
    "ㄌㄡˋ" : [
      "陋",
      "鏤",
      "露",
      "漏"
    ],
    "ㄑㄧㄥˇ" : [
      "頃",
      "請"
    ],
    "ㄉㄚˊ" : [
      "達",
      "答"
    ],
    "ㄎㄨㄟ" : [
      "虧",
      "窺",
      "盔"
    ],
    "ㄉㄚˋ" : [
      "大"
    ],
    "ㄏㄨㄚˊ" : [
      "划",
      "滑",
      "譁",
      "猾",
      "劃",
      "豁"
    ],
    "ㄕㄟˊ" : [
      "誰"
    ],
    "ㄈㄥˊ" : [
      "逢",
      "縫",
      "馮"
    ],
    "ㄍㄨㄢˇ" : [
      "館",
      "管"
    ],
    "ㄈㄚ" : [
      "伐",
      "發"
    ],
    "ㄎㄜˇ" : [
      "渴",
      "可",
      "坷"
    ],
    "ㄈㄥˋ" : [
      "奉",
      "諷",
      "縫",
      "鳳",
      "風",
      "俸"
    ],
    "ㄅㄞˊ" : [
      "白"
    ],
    "ㄏㄨㄚˋ" : [
      "樺",
      "話",
      "劃",
      "畫",
      "化"
    ],
    "ㄘㄨㄢˋ" : [
      "竄"
    ],
    "ㄅㄞˋ" : [
      "敗",
      "拜"
    ],
    "ㄎㄨㄢ" : [
      "寬"
    ],
    "ㄈㄟ" : [
      "妃",
      "菲",
      "啡",
      "飛",
      "非",
      "扉"
    ],
    "ㄊㄠˇ" : [
      "討"
    ],
    "ㄎㄨㄣ" : [
      "崑",
      "昆",
      "坤"
    ],
    "ㄎㄜˊ" : [
      "咳",
      "殼"
    ],
    "ㄑㄧㄥˊ" : [
      "擎",
      "情",
      "晴"
    ],
    "ㄎㄨㄤ" : [
      "框",
      "筐",
      "眶"
    ],
    "ㄎㄜˋ" : [
      "剋",
      "刻",
      "嗑",
      "克",
      "客",
      "課",
      "可"
    ],
    "ㄈㄢ" : [
      "翻",
      "番",
      "蕃"
    ],
    "ㄈㄣ" : [
      "分",
      "芬",
      "紛",
      "吩",
      "氛"
    ],
    "ㄎㄨㄥ" : [
      "空"
    ],
    "ㄓㄞˇ" : [
      "窄"
    ],
    "ㄈㄤ" : [
      "方",
      "芳",
      "坊"
    ],
    "ㄑㄧㄥˋ" : [
      "親",
      "罄",
      "慶"
    ],
    "ㄗㄚˊ" : [
      "砸",
      "雜",
      "咱"
    ],
    "ㄊㄠˊ" : [
      "逃",
      "淘",
      "桃",
      "陶",
      "啕",
      "濤",
      "萄"
    ],
    "ㄈㄥ" : [
      "峰",
      "鋒",
      "烽",
      "楓",
      "蜂",
      "封",
      "風",
      "瘋",
      "丰",
      "豐"
    ],
    "ㄜˊ" : [
      "訛",
      "峨",
      "蚵",
      "蛾",
      "哦",
      "額",
      "俄",
      "鵝",
      "娥"
    ],
    "ㄒㄩˇ" : [
      "栩",
      "許",
      "咻",
      "煦"
    ],
    "ㄜˋ" : [
      "餓",
      "鱷",
      "堊",
      "噩",
      "愕",
      "厄",
      "遏",
      "顎",
      "呃",
      "惡",
      "扼"
    ],
    "ㄊㄠˋ" : [
      "套"
    ],
    "ㄖㄥˊ" : [
      "仍"
    ],
    "ㄍㄨㄢˋ" : [
      "鸛",
      "罐",
      "慣",
      "觀",
      "灌",
      "冠",
      "貫"
    ],
    "ㄈㄨ" : [
      "夫",
      "膚",
      "孵",
      "敷",
      "傅"
    ],
    "ㄏㄢˇ" : [
      "罕",
      "喊"
    ],
    "ㄏㄨㄣˊ" : [
      "魂",
      "渾"
    ],
    "ㄓㄞˊ" : [
      "宅"
    ],
    "ㄆㄤˊ" : [
      "龐",
      "膀",
      "旁",
      "徬",
      "彷",
      "螃",
      "傍"
    ],
    "ㄓㄨㄥˇ" : [
      "踵",
      "冢",
      "腫",
      "塚",
      "種"
    ],
    "ㄓㄞˋ" : [
      "寨",
      "債"
    ],
    "ㄆㄧㄥˊ" : [
      "瓶",
      "蘋",
      "憑",
      "屏",
      "萍",
      "秤",
      "評",
      "坪",
      "馮",
      "平"
    ],
    "ㄒㄩˊ" : [
      "徐"
    ],
    "˙ㄧㄚ" : [
      "呀"
    ],
    "ㄆㄤˋ" : [
      "胖"
    ],
    "ㄌㄧㄡ" : [
      "溜"
    ],
    "ㄙㄨㄟˇ" : [
      "髓"
    ],
    "ㄏㄨㄣˋ" : [
      "混"
    ],
    "ㄘㄠˇ" : [
      "草"
    ],
    "ㄐㄧㄡˇ" : [
      "灸",
      "酒",
      "九",
      "韭",
      "玖",
      "久"
    ],
    "ㄒㄩˋ" : [
      "蓄",
      "序",
      "恤",
      "旭",
      "敘",
      "絮",
      "續",
      "緒",
      "婿",
      "畜"
    ],
    "ㄏㄢˊ" : [
      "汗",
      "函",
      "寒",
      "韓",
      "涵",
      "含"
    ],
    "ㄑㄩㄝ" : [
      "闕",
      "缺"
    ],
    "ㄆㄧㄥˋ" : [
      "聘"
    ],
    "ㄈㄟˇ" : [
      "悱",
      "翡",
      "斐",
      "菲",
      "匪"
    ],
    "ㄏㄢˋ" : [
      "汗",
      "悍",
      "翰",
      "瀚",
      "銲",
      "撼",
      "旱",
      "憾",
      "和"
    ],
    "˙ㄧㄝ" : [
      "吔"
    ],
    "ㄔㄤˇ" : [
      "場",
      "敞",
      "廠"
    ],
    "ㄓㄚ" : [
      "查",
      "喳",
      "渣",
      "扎"
    ],
    "ㄘㄠˊ" : [
      "嘈",
      "槽",
      "曹"
    ],
    "ㄒㄧㄢˇ" : [
      "鮮",
      "蘚",
      "險",
      "顯"
    ],
    "ㄌㄧㄥ" : [
      "拎"
    ],
    "ㄓㄜ" : [
      "遮",
      "折"
    ],
    "ㄈㄟˊ" : [
      "肥"
    ],
    "ㄎㄨㄟˇ" : [
      "傀"
    ],
    "ㄙㄨㄟˊ" : [
      "隨",
      "隋"
    ],
    "ㄓㄞ" : [
      "齋",
      "摘"
    ],
    "ㄈㄟˋ" : [
      "肺",
      "芾",
      "費",
      "沸",
      "廢",
      "吠"
    ],
    "ㄑㄩㄢ" : [
      "圈"
    ],
    "ㄔㄤˊ" : [
      "嚐",
      "長",
      "嘗",
      "腸",
      "常",
      "償",
      "徜",
      "嫦",
      "裳"
    ],
    "ㄓㄨㄥˋ" : [
      "仲",
      "重",
      "眾",
      "種"
    ],
    "ㄓㄠ" : [
      "朝",
      "昭",
      "招",
      "著"
    ],
    "ㄏㄨㄚ" : [
      "嘩",
      "花",
      "化"
    ],
    "ㄍㄡˇ" : [
      "苟",
      "狗",
      "枸"
    ],
    "ㄔㄤˋ" : [
      "悵",
      "唱",
      "倡",
      "暢"
    ],
    "ㄙㄨㄟˋ" : [
      "邃",
      "歲",
      "遂",
      "碎",
      "穗",
      "祟",
      "隧"
    ],
    "ㄓㄡ" : [
      "粥",
      "週",
      "州",
      "洲",
      "舟",
      "啁",
      "周"
    ],
    "ㄓㄢ" : [
      "詹",
      "瞻",
      "沾",
      "占",
      "氈"
    ],
    "ㄧˇ" : [
      "已",
      "以",
      "椅",
      "矣",
      "蟻",
      "倚",
      "乙"
    ],
    "ㄐㄧㄡˋ" : [
      "疚",
      "桕",
      "鷲",
      "舊",
      "舅",
      "臼",
      "救",
      "究",
      "就",
      "咎"
    ],
    "ㄊㄚˇ" : [
      "塔"
    ],
    "ㄓㄣ" : [
      "針",
      "斟",
      "楨",
      "真",
      "珍",
      "偵",
      "貞",
      "禎",
      "甄"
    ],
    "ㄑㄩㄣˊ" : [
      "群",
      "裙"
    ],
    "ㄓㄤ" : [
      "璋",
      "樟",
      "章",
      "張",
      "蟑",
      "漳",
      "彰"
    ],
    "ㄑㄩㄥ" : [
      "穹"
    ],
    "ㄇㄧㄢˇ" : [
      "冕",
      "免",
      "緬",
      "靦",
      "勉"
    ],
    "ㄉㄥˇ" : [
      "等"
    ],
    "ㄓㄥ" : [
      "正",
      "掙",
      "爭",
      "猙",
      "崢",
      "怔",
      "睜",
      "箏",
      "徵",
      "征",
      "蒸",
      "癥",
      "諍"
    ],
    "ㄒㄧㄢˊ" : [
      "鹹",
      "閒",
      "銜",
      "絃",
      "嫌",
      "嫻",
      "咸",
      "賢",
      "弦"
    ],
    "ㄧˊ" : [
      "疑",
      "胰",
      "夷",
      "怡",
      "儀",
      "宜",
      "迤",
      "蛇",
      "遺",
      "台",
      "貽",
      "咦",
      "飴",
      "移",
      "頤",
      "姨"
    ],
    "ㄧˋ" : [
      "亦",
      "藝",
      "疫",
      "逸",
      "奕",
      "縊",
      "驛",
      "誼",
      "洩",
      "翌",
      "義",
      "羿",
      "溢",
      "繹",
      "億",
      "艾",
      "議",
      "譯",
      "憶",
      "衣",
      "屹",
      "蜴",
      "射",
      "意",
      "役",
      "佚",
      "曳",
      "抑",
      "易",
      "益",
      "懿",
      "翼",
      "異",
      "毅",
      "裔",
      "邑"
    ],
    "ㄎㄨㄟˊ" : [
      "揆",
      "睽",
      "魁",
      "逵",
      "葵"
    ],
    "ㄍㄡˋ" : [
      "夠",
      "搆",
      "構",
      "勾",
      "垢",
      "購"
    ],
    "ㄓㄨ" : [
      "朱",
      "株",
      "諸",
      "藷",
      "蛛",
      "珠",
      "侏",
      "豬",
      "茱"
    ],
    "ㄒㄧㄢˋ" : [
      "見",
      "餡",
      "獻",
      "腺",
      "羨",
      "陷",
      "限",
      "縣",
      "憲",
      "現",
      "線"
    ],
    "ㄏㄨㄟ" : [
      "揮",
      "灰",
      "輝",
      "恢",
      "徽",
      "暉"
    ],
    "ㄊㄚˋ" : [
      "踏",
      "蹋",
      "榻",
      "獺",
      "沓",
      "拓"
    ],
    "ㄎㄨㄟˋ" : [
      "餽",
      "潰",
      "喟",
      "饋",
      "愧",
      "匱"
    ],
    "ㄉㄥˋ" : [
      "蹬",
      "凳",
      "瞪",
      "鄧"
    ],
    "ㄆㄞˊ" : [
      "牌",
      "排",
      "徘"
    ],
    "ㄨㄛˇ" : [
      "我"
    ],
    "ㄔㄨㄢˇ" : [
      "舛",
      "喘"
    ],
    "ㄆㄞˋ" : [
      "派",
      "湃"
    ],
    "ㄏㄨㄢ" : [
      "歡"
    ],
    "ㄇㄧㄢˊ" : [
      "棉",
      "眠",
      "綿"
    ],
    "ㄋㄠˇ" : [
      "瑙",
      "腦",
      "惱"
    ],
    "ㄏㄨㄣ" : [
      "昏",
      "婚"
    ],
    "ㄆㄚ" : [
      "啪",
      "趴"
    ],
    "ㄏㄜˊ" : [
      "劾",
      "何",
      "閤",
      "闔",
      "涸",
      "核",
      "荷",
      "和",
      "河",
      "盒",
      "合",
      "禾",
      "褐"
    ],
    "ㄆㄛ" : [
      "坡",
      "潑"
    ],
    "ㄏㄨㄤ" : [
      "慌",
      "荒"
    ],
    "ㄌㄩㄝˋ" : [
      "掠",
      "略"
    ],
    "ㄇㄧㄢˋ" : [
      "麵",
      "面"
    ],
    "ㄏㄜˋ" : [
      "嚇",
      "喝",
      "荷",
      "和",
      "賀",
      "鶴",
      "赫"
    ],
    "ㄍㄨㄛˇ" : [
      "粿",
      "裹",
      "果"
    ],
    "ㄏㄨㄥ" : [
      "轟",
      "烘",
      "哄"
    ],
    "ㄆㄞ" : [
      "拍"
    ],
    "ㄇㄤˇ" : [
      "蟒",
      "莽"
    ],
    "ㄨㄛˋ" : [
      "握",
      "渥",
      "喔",
      "臥",
      "沃"
    ],
    "ㄋㄠˊ" : [
      "撓"
    ],
    "ㄆㄟ" : [
      "胚"
    ],
    "ㄆㄠ" : [
      "泡",
      "拋"
    ],
    "ㄘㄨㄛˋ" : [
      "措",
      "挫",
      "撮",
      "厝",
      "錯"
    ],
    "ㄋㄠˋ" : [
      "鬧"
    ],
    "ㄉㄨㄢˇ" : [
      "短"
    ],
    "ㄔㄨㄢˊ" : [
      "船",
      "傳"
    ],
    "ㄆㄢ" : [
      "攀",
      "潘"
    ],
    "ㄗㄥˋ" : [
      "贈"
    ],
    "ㄆㄣ" : [
      "噴"
    ],
    "ㄋㄧㄤˊ" : [
      "娘"
    ],
    "ㄔㄞˊ" : [
      "柴"
    ],
    "ㄇㄤˊ" : [
      "盲",
      "芒",
      "忙",
      "茫"
    ],
    "ㄆㄤ" : [
      "磅",
      "滂",
      "乓"
    ],
    "ㄔㄨㄢˋ" : [
      "串"
    ],
    "ㄆㄥ" : [
      "砰",
      "烹",
      "澎"
    ],
    "ㄍㄨㄛˊ" : [
      "國"
    ],
    "ㄋㄧㄤˋ" : [
      "釀"
    ],
    "ㄙㄠˇ" : [
      "掃",
      "嫂"
    ],
    "ㄆㄧ" : [
      "劈",
      "霹",
      "被",
      "披",
      "批",
      "匹"
    ],
    "ㄒㄩㄝ" : [
      "薛",
      "靴"
    ],
    "ㄆㄨ" : [
      "撲",
      "仆",
      "鋪"
    ],
    "ㄉㄟˇ" : [
      "得"
    ],
    "ㄍㄨㄛˋ" : [
      "過"
    ],
    "ㄖㄨㄣˋ" : [
      "閏",
      "潤"
    ],
    "ㄕㄤˇ" : [
      "賞",
      "晌",
      "上"
    ],
    "ㄍㄨㄤˇ" : [
      "獷",
      "廣"
    ],
    "˙ㄏㄨㄛ" : [
      "和"
    ],
    "ㄅㄣˇ" : [
      "本",
      "畚"
    ],
    "ㄙㄠˋ" : [
      "掃",
      "燥"
    ],
    "ㄉㄨㄢˋ" : [
      "斷",
      "鍛",
      "段",
      "緞"
    ],
    "ㄊㄧㄠˇ" : [
      "挑",
      "窕"
    ],
    "˙ㄊㄡ" : [
      "頭"
    ],
    "ㄐㄧㄚˇ" : [
      "舺",
      "假",
      "賈",
      "甲"
    ],
    "ㄒㄩㄢ" : [
      "軒",
      "喧",
      "宣",
      "暄",
      "嬛"
    ],
    "ㄏㄨㄥˇ" : [
      "哄"
    ],
    "ㄎㄡˇ" : [
      "口"
    ],
    "ㄒㄩㄣ" : [
      "薰",
      "醺",
      "燻",
      "勛"
    ],
    "ㄕㄨㄟˇ" : [
      "水"
    ],
    "ㄕㄤˋ" : [
      "尚",
      "上"
    ],
    "ㄧㄠˇ" : [
      "杳",
      "舀",
      "咬",
      "窈"
    ],
    "ㄋㄚˇ" : [
      "哪"
    ],
    "ㄌㄧㄡˇ" : [
      "柳"
    ],
    "ㄅㄣˋ" : [
      "笨"
    ],
    "ㄒㄩㄥ" : [
      "胸",
      "凶",
      "洶",
      "兄",
      "兇",
      "匈"
    ],
    "ㄩㄝ" : [
      "約",
      "曰"
    ],
    "ㄊㄧㄠˊ" : [
      "調",
      "迢",
      "條"
    ],
    "ㄍㄨㄤˋ" : [
      "逛"
    ],
    "ㄧㄠˊ" : [
      "遙",
      "瑤",
      "餚",
      "淆",
      "肴",
      "搖",
      "謠",
      "堯",
      "窯",
      "姚"
    ],
    "ㄇㄞˇ" : [
      "買"
    ],
    "ㄎㄡˋ" : [
      "寇",
      "蔻",
      "叩",
      "扣"
    ],
    "ㄐㄧㄚˊ" : [
      "夾",
      "浹",
      "頰",
      "莢"
    ],
    "ㄋㄚˊ" : [
      "南",
      "拿"
    ],
    "ㄩㄢ" : [
      "鴛",
      "淵",
      "冤",
      "宛",
      "鳶"
    ],
    "ㄓㄣˇ" : [
      "疹",
      "診",
      "枕"
    ],
    "ㄧㄠˋ" : [
      "藥",
      "樂",
      "要",
      "曜",
      "鑰",
      "耀"
    ],
    "ㄏㄨㄥˊ" : [
      "閎",
      "訌",
      "洪",
      "虹",
      "宏",
      "紅",
      "弘",
      "鴻"
    ],
    "ㄋㄚˋ" : [
      "捺",
      "鈉",
      "納",
      "吶",
      "娜",
      "那"
    ],
    "ㄗㄟˊ" : [
      "賊"
    ],
    "ㄩㄣ" : [
      "暈"
    ],
    "ㄊㄨㄟˇ" : [
      "腿"
    ],
    "ㄊㄧㄠˋ" : [
      "跳",
      "眺"
    ],
    "ㄊㄥˊ" : [
      "疼",
      "騰",
      "籐",
      "藤"
    ],
    "ㄐㄧㄚˋ" : [
      "價",
      "假",
      "嫁",
      "駕",
      "架"
    ],
    "ㄩㄥ" : [
      "雍",
      "傭",
      "庸"
    ],
    "ㄑㄧ" : [
      "棲",
      "柒",
      "妻",
      "萋",
      "淒",
      "悽",
      "沏",
      "七",
      "戚",
      "漆",
      "欺"
    ],
    "ㄌㄧㄡˊ" : [
      "琉",
      "榴",
      "流",
      "劉",
      "瘤",
      "瀏",
      "留",
      "硫"
    ],
    "ㄇㄞˊ" : [
      "霾",
      "埋"
    ],
    "ㄐㄧㄣˇ" : [
      "瑾",
      "槿",
      "儘",
      "僅",
      "謹",
      "緊",
      "錦",
      "菫"
    ],
    "ㄕㄨㄟˋ" : [
      "說",
      "睡",
      "稅"
    ],
    "ㄇㄞˋ" : [
      "麥",
      "脈",
      "賣",
      "邁"
    ],
    "ㄑㄩ" : [
      "嶇",
      "軀",
      "驅",
      "蛆",
      "屈",
      "曲",
      "區",
      "趨"
    ],
    "ㄙㄚˇ" : [
      "撒",
      "灑"
    ],
    "ㄌㄧㄡˋ" : [
      "陸",
      "溜",
      "六"
    ],
    "ㄌㄠˇ" : [
      "老",
      "硓"
    ],
    "ㄓㄣˋ" : [
      "朕",
      "振",
      "陣",
      "鎮",
      "震",
      "賑",
      "枕"
    ],
    "ㄒㄧㄤˇ" : [
      "享",
      "想",
      "響",
      "饗"
    ],
    "ㄊㄨㄟˊ" : [
      "頹"
    ],
    "ㄈㄤˇ" : [
      "仿",
      "訪",
      "彷",
      "紡"
    ],
    "ㄌㄠˊ" : [
      "嘮",
      "牢",
      "勞"
    ],
    "ㄙㄚˋ" : [
      "薩",
      "卅"
    ],
    "ㄌㄠˋ" : [
      "烙",
      "落",
      "潦",
      "勞"
    ],
    "ㄘㄥˊ" : [
      "層",
      "曾"
    ],
    "ㄊㄨㄟˋ" : [
      "退",
      "蛻"
    ],
    "ㄈㄤˊ" : [
      "妨",
      "肪",
      "防",
      "房",
      "坊"
    ],
    "ㄐㄧㄣˋ" : [
      "進",
      "浸",
      "近",
      "禁",
      "盡",
      "晉"
    ],
    "ㄕㄞˋ" : [
      "晒"
    ],
    "ㄈㄤˋ" : [
      "放"
    ],
    "ㄑㄩㄥˊ" : [
      "瓊",
      "窮"
    ],
    "ㄧㄚˇ" : [
      "雅",
      "啞"
    ],
    "ㄒㄧㄤˊ" : [
      "詳",
      "翔",
      "降",
      "祥",
      "庠"
    ],
    "ㄘˇ" : [
      "此"
    ],
    "ㄉㄨㄛˇ" : [
      "朵",
      "躲"
    ],
    "ㄒㄧㄤˋ" : [
      "嚮",
      "巷",
      "橡",
      "項",
      "像",
      "象",
      "相",
      "向"
    ],
    "ㄘˊ" : [
      "磁",
      "慈",
      "詞",
      "瓷",
      "辭",
      "茲",
      "茨",
      "祠"
    ],
    "ㄖㄤˇ" : [
      "壤",
      "嚷"
    ],
    "ㄘˋ" : [
      "刺",
      "伺",
      "次"
    ],
    "ㄧㄚˊ" : [
      "芽",
      "涯",
      "衙",
      "牙",
      "枒",
      "蚜"
    ],
    "ㄉㄧㄥˇ" : [
      "鼎",
      "頂"
    ],
    "ㄔㄨㄛˋ" : [
      "輟",
      "啜",
      "綽"
    ],
    "ㄧㄚˋ" : [
      "亞",
      "訝",
      "揠",
      "軋",
      "埡"
    ],
    "ㄅㄧㄣˋ" : [
      "臏",
      "鬢"
    ],
    "ㄔㄨㄤˇ" : [
      "闖"
    ],
    "ㄋㄧㄝˋ" : [
      "囁",
      "躡",
      "聶"
    ],
    "ㄖㄤˊ" : [
      "攘"
    ],
    "ㄏㄡˇ" : [
      "吼"
    ],
    "ㄖㄤˋ" : [
      "讓"
    ],
    "ㄑㄧㄠˇ" : [
      "悄",
      "巧"
    ],
    "ㄆㄣˊ" : [
      "盆"
    ],
    "ㄉㄨㄛˊ" : [
      "奪"
    ],
    "ㄌㄚˇ" : [
      "喇"
    ],
    "ㄆㄣˋ" : [
      "噴"
    ],
    "ㄒㄩㄢˇ" : [
      "選"
    ],
    "ㄏㄚ" : [
      "哈"
    ],
    "ㄉㄨㄛˋ" : [
      "踱",
      "跺",
      "惰",
      "墮",
      "舵",
      "度",
      "咄"
    ],
    "˙ㄕㄤ" : [
      "裳"
    ],
    "ㄏㄡˊ" : [
      "喉",
      "猴",
      "侯"
    ],
    "ㄧㄚ" : [
      "鴨",
      "鴉",
      "椏",
      "啞",
      "壓",
      "押",
      "呀",
      "丫"
    ],
    "ㄏㄜ" : [
      "喝",
      "呵"
    ],
    "ㄏㄡˋ" : [
      "逅",
      "後",
      "候",
      "厚",
      "后"
    ],
    "ㄉㄧㄥˋ" : [
      "訂",
      "釘",
      "定"
    ],
    "ㄧㄛ" : [
      "唷"
    ],
    "ㄔㄨㄤˊ" : [
      "床",
      "幢"
    ],
    "ㄏㄞ" : [
      "嗨",
      "咳"
    ],
    "ㄧㄝ" : [
      "噎"
    ],
    "ㄌㄚˋ" : [
      "辣",
      "臘",
      "蠟",
      "落"
    ],
    "ㄏㄟ" : [
      "嘿",
      "黑"
    ],
    "ㄋㄥˊ" : [
      "能"
    ],
    "ㄆㄧㄠˇ" : [
      "漂",
      "瞟"
    ],
    "ㄑㄧㄠˊ" : [
      "橋",
      "喬",
      "僑",
      "憔",
      "樵",
      "瞧",
      "翹"
    ],
    "ㄔㄨㄤˋ" : [
      "愴",
      "創"
    ],
    "ㄏㄠ" : [
      "蒿"
    ],
    "ㄌㄧㄚˇ" : [
      "倆"
    ],
    "ㄧㄠ" : [
      "妖",
      "要",
      "夭",
      "腰",
      "喲",
      "吆",
      "么",
      "邀"
    ],
    "ㄖㄨㄥˊ" : [
      "熔",
      "榮",
      "榕",
      "蓉",
      "溶",
      "容",
      "絨",
      "茸",
      "融",
      "鎔",
      "嶸"
    ],
    "ㄏㄢ" : [
      "酣",
      "憨",
      "鼾"
    ],
    "ㄧㄡ" : [
      "悠",
      "優",
      "憂",
      "攸",
      "幽"
    ],
    "ㄐㄧˇ" : [
      "己",
      "擠",
      "脊",
      "給",
      "濟",
      "幾"
    ],
    "ㄑㄧㄠˋ" : [
      "峭",
      "竅",
      "俏",
      "翹"
    ],
    "ㄧㄢ" : [
      "焉",
      "燕",
      "奄",
      "淹",
      "醃",
      "嫣",
      "咽",
      "殷",
      "菸",
      "煙"
    ],
    "ㄔㄣˊ" : [
      "塵",
      "陳",
      "辰",
      "臣",
      "宸",
      "忱",
      "沉",
      "晨"
    ],
    "ㄒㄩㄢˊ" : [
      "旋",
      "懸",
      "玄",
      "漩"
    ],
    "ㄧㄣ" : [
      "因",
      "陰",
      "瘖",
      "殷",
      "音",
      "茵",
      "姻"
    ],
    "ㄏㄥ" : [
      "亨",
      "哼"
    ],
    "ㄍㄠˇ" : [
      "搞",
      "攪",
      "稿"
    ],
    "ㄧㄤ" : [
      "鴦",
      "央",
      "殃",
      "秧"
    ],
    "ㄔㄣˋ" : [
      "襯",
      "趁"
    ],
    "ㄧㄥ" : [
      "鶯",
      "瑛",
      "鸚",
      "罌",
      "應",
      "英",
      "嬰",
      "櫻",
      "鷹"
    ],
    "ㄏㄨㄞˊ" : [
      "踝",
      "淮",
      "槐",
      "懷",
      "徊"
    ],
    "ㄒㄩㄢˋ" : [
      "旋",
      "炫",
      "眩",
      "渲",
      "絢"
    ],
    "ㄐㄧˊ" : [
      "亟",
      "棘",
      "疾",
      "汲",
      "集",
      "擊",
      "輯",
      "藉",
      "急",
      "寂",
      "極",
      "岌",
      "唧",
      "及",
      "級",
      "嫉",
      "瘠",
      "即",
      "吉",
      "吃",
      "籍"
    ],
    "ㄏㄨ" : [
      "惚",
      "虎",
      "忽",
      "呼",
      "乎"
    ],
    "ㄆㄧㄠˊ" : [
      "瓢"
    ],
    "ㄉㄤˇ" : [
      "擋",
      "檔",
      "黨",
      "當"
    ],
    "ㄐㄧˋ" : [
      "妓",
      "髻",
      "劑",
      "記",
      "計",
      "悸",
      "際",
      "冀",
      "繫",
      "繼",
      "寄",
      "既",
      "季",
      "忌",
      "暨",
      "紀",
      "祭",
      "濟",
      "技"
    ],
    "ㄊㄧㄢˇ" : [
      "舔",
      "腆",
      "靦"
    ],
    "ㄏㄨㄞˋ" : [
      "壞"
    ],
    "ㄋㄨㄥˊ" : [
      "農",
      "膿",
      "濃"
    ],
    "ㄍㄠˋ" : [
      "告"
    ],
    "ㄆㄧㄠˋ" : [
      "漂",
      "票"
    ],
    "ㄅㄨˇ" : [
      "捕",
      "哺",
      "卜",
      "補"
    ],
    "ㄋㄨㄥˋ" : [
      "弄"
    ],
    "ㄌㄧㄣˇ" : [
      "凜"
    ],
    "ㄉㄤˋ" : [
      "蕩",
      "宕",
      "盪",
      "當"
    ],
    "ㄒㄧㄝˇ" : [
      "寫",
      "血"
    ],
    "ㄨㄚˇ" : [
      "瓦"
    ],
    "ㄎㄨㄚˇ" : [
      "垮"
    ],
    "ㄧㄥˇ" : [
      "潁",
      "穎",
      "影"
    ],
    "ㄊㄧㄢˊ" : [
      "闐",
      "填",
      "恬",
      "田",
      "甜"
    ],
    "ㄋㄟˇ" : [
      "餒"
    ],
    "ㄅㄨˋ" : [
      "步",
      "布",
      "怖",
      "佈",
      "簿",
      "埠",
      "部",
      "不"
    ],
    "ㄨㄚˊ" : [
      "娃"
    ],
    "ㄙㄨㄣˇ" : [
      "損",
      "筍"
    ],
    "ㄨㄚˋ" : [
      "襪"
    ],
    "ㄧㄥˊ" : [
      "瑩",
      "蠅",
      "迎",
      "縈",
      "螢",
      "營",
      "盈",
      "贏"
    ],
    "ㄌㄧㄣˊ" : [
      "麟",
      "遴",
      "磷",
      "淋",
      "琳",
      "鄰",
      "臨",
      "霖",
      "鱗",
      "林"
    ],
    "ㄒㄧㄝˊ" : [
      "脅",
      "鞋",
      "斜",
      "偕",
      "協",
      "邪",
      "諧"
    ],
    "ㄓㄨˇ" : [
      "囑",
      "矚",
      "屬",
      "貯",
      "拄",
      "主",
      "煮"
    ],
    "ㄐㄧㄥˇ" : [
      "井",
      "頸",
      "阱",
      "警",
      "憬",
      "景"
    ],
    "ㄧㄥˋ" : [
      "應",
      "映",
      "硬"
    ],
    "ㄋㄟˋ" : [
      "內"
    ],
    "ㄖˋ" : [
      "日"
    ],
    "ㄌㄨㄢˇ" : [
      "卵"
    ],
    "ㄌㄧㄣˋ" : [
      "藺",
      "吝"
    ],
    "ㄗㄤˋ" : [
      "藏",
      "奘",
      "臟",
      "葬"
    ],
    "ㄒㄧㄝˋ" : [
      "契",
      "邂",
      "解",
      "榭",
      "洩",
      "屑",
      "瀉",
      "謝",
      "懈",
      "蟹",
      "卸",
      "泄",
      "械"
    ],
    "ㄇㄣˊ" : [
      "門",
      "們"
    ],
    "ㄇㄣˋ" : [
      "悶",
      "燜"
    ],
    "ㄎㄨㄚˋ" : [
      "跨"
    ],
    "ㄗㄨㄢˋ" : [
      "鑽"
    ],
    "ㄓㄨˊ" : [
      "朮",
      "逐",
      "燭",
      "竹",
      "筑",
      "築",
      "竺"
    ],
    "ㄌㄥˇ" : [
      "冷"
    ],
    "ㄓㄨˋ" : [
      "助",
      "柱",
      "駐",
      "住",
      "杼",
      "註",
      "蛀",
      "鑄",
      "佇",
      "祝",
      "著",
      "注"
    ],
    "˙ㄉㄜ" : [
      "地",
      "的",
      "得"
    ],
    "ㄎㄨㄣˇ" : [
      "捆",
      "壼",
      "綑"
    ],
    "ㄉㄞˇ" : [
      "歹",
      "逮"
    ],
    "ㄅㄧㄥˇ" : [
      "柄",
      "餅",
      "炳",
      "屏",
      "稟",
      "秉",
      "丙"
    ],
    "ㄍㄚˊ" : [
      "軋"
    ],
    "ㄕㄣˇ" : [
      "審",
      "沈",
      "嬸"
    ],
    "ㄍㄚˋ" : [
      "尬"
    ],
    "ㄌㄨㄢˊ" : [
      "巒"
    ],
    "ㄌㄥˊ" : [
      "楞",
      "稜"
    ],
    "ㄍㄚ" : [
      "嘎"
    ],
    "ㄇㄧㄝˋ" : [
      "篾",
      "滅",
      "蔑"
    ],
    "ㄐㄧㄥˋ" : [
      "逕",
      "淨",
      "境",
      "勁",
      "敬",
      "徑",
      "鏡",
      "靖",
      "靜",
      "竟",
      "競"
    ],
    "ㄅㄢˇ" : [
      "粄",
      "闆",
      "板",
      "阪",
      "版"
    ],
    "ㄌㄥˋ" : [
      "怔",
      "楞",
      "愣"
    ],
    "ㄍㄜ" : [
      "鴿",
      "割",
      "擱",
      "胳",
      "哥",
      "咯",
      "歌",
      "戈"
    ],
    "ㄌㄨㄢˋ" : [
      "亂"
    ],
    "ㄑㄧˇ" : [
      "杞",
      "啟",
      "豈",
      "稽",
      "綺",
      "起",
      "乞"
    ],
    "ㄉㄞˋ" : [
      "逮",
      "大",
      "怠",
      "帶",
      "岱",
      "待",
      "代",
      "貸",
      "殆",
      "袋",
      "戴",
      "黛"
    ],
    "ㄕㄣˊ" : [
      "什",
      "神",
      "甚"
    ],
    "ㄍㄞ" : [
      "該",
      "賅"
    ],
    "ㄎㄠˇ" : [
      "烤",
      "拷",
      "考"
    ],
    "ㄕㄣˋ" : [
      "腎",
      "滲",
      "慎",
      "葚",
      "甚"
    ],
    "ㄐㄧㄚ" : [
      "加",
      "嘉",
      "家",
      "迦",
      "伽",
      "傢",
      "佳",
      "茄",
      "枷"
    ],
    "ㄍㄠ" : [
      "膏",
      "糕",
      "高",
      "羔",
      "篙",
      "睪"
    ],
    "ㄘㄨㄟˇ" : [
      "璀"
    ],
    "ㄍㄡ" : [
      "溝",
      "篝",
      "勾",
      "句",
      "鉤"
    ],
    "ㄍㄢ" : [
      "柑",
      "肝",
      "杆",
      "竿",
      "尷",
      "甘",
      "乾",
      "干"
    ],
    "ㄅㄢˋ" : [
      "半",
      "拌",
      "瓣",
      "辦",
      "絆",
      "伴",
      "扮"
    ],
    "ㄡˇ" : [
      "嘔",
      "藕",
      "偶"
    ],
    "ㄎㄨㄣˋ" : [
      "困",
      "睏"
    ],
    "ㄑㄧˊ" : [
      "歧",
      "崎",
      "期",
      "棋",
      "奇",
      "齊",
      "淇",
      "琪",
      "琦",
      "鰭",
      "其",
      "旗",
      "臍",
      "祇",
      "祈",
      "騎",
      "畦"
    ],
    "ㄍㄣ" : [
      "跟",
      "根"
    ],
    "ㄗㄞˇ" : [
      "載",
      "宰"
    ],
    "ㄍㄤ" : [
      "亢",
      "剛",
      "缸",
      "崗",
      "岡",
      "肛",
      "綱",
      "鋼",
      "扛"
    ],
    "ㄊㄤˇ" : [
      "躺",
      "淌",
      "倘"
    ],
    "ㄅㄧㄥˋ" : [
      "摒",
      "並",
      "併",
      "病",
      "并"
    ],
    "ㄑㄧˋ" : [
      "亟",
      "棄",
      "汽",
      "砌",
      "契",
      "器",
      "憩",
      "迄",
      "企",
      "緝",
      "泣",
      "氣"
    ],
    "ㄐㄧㄝ" : [
      "接",
      "揭",
      "階",
      "結",
      "偕",
      "街",
      "皆"
    ],
    "ㄍㄥ" : [
      "羹",
      "更",
      "庚",
      "耕"
    ],
    "ㄡˋ" : [
      "嘔"
    ],
    "ㄎㄠˋ" : [
      "靠"
    ],
    "ㄍㄨ" : [
      "骨",
      "辜",
      "家",
      "箍",
      "孤",
      "估",
      "咕",
      "呱",
      "沽",
      "菇",
      "姑"
    ],
    "ㄓㄢˇ" : [
      "嶄",
      "展",
      "輾",
      "斬",
      "盞"
    ],
    "ㄑㄧㄢˇ" : [
      "遣",
      "淺",
      "譴"
    ],
    "ㄆㄨˇ" : [
      "圃",
      "浦",
      "譜",
      "埔",
      "普"
    ],
    "ㄊㄤˊ" : [
      "糖",
      "棠",
      "塘",
      "膛",
      "唐",
      "螳",
      "堂"
    ],
    "ㄐㄧㄠ" : [
      "交",
      "跤",
      "蕉",
      "驕",
      "焦",
      "椒",
      "蛟",
      "嬌",
      "教",
      "澆",
      "礁",
      "郊",
      "膠"
    ],
    "ㄍㄨㄟˇ" : [
      "軌",
      "詭",
      "鬼",
      "癸",
      "晷"
    ],
    "ㄗㄞˋ" : [
      "在",
      "再",
      "載"
    ],
    "ㄊㄤˋ" : [
      "燙",
      "趟"
    ],
    "ㄐㄧㄡ" : [
      "糾",
      "揪",
      "鳩",
      "啾",
      "赳"
    ],
    "ㄐㄧㄢ" : [
      "奸",
      "肩",
      "間",
      "兼",
      "緘",
      "箋",
      "堅",
      "尖",
      "艱",
      "監",
      "煎",
      "姦"
    ],
    "ㄆㄨˊ" : [
      "蹼",
      "脯",
      "僕",
      "樸",
      "葡",
      "菩",
      "匍",
      "蒲",
      "璞"
    ],
    "ㄘㄨㄟˋ" : [
      "粹",
      "淬",
      "脆",
      "悴",
      "翠",
      "萃"
    ],
    "ㄨㄥˇ" : [
      "蓊"
    ],
    "ㄌㄟˇ" : [
      "蕾",
      "壘",
      "儡",
      "累",
      "耒"
    ],
    "ㄓㄢˋ" : [
      "棧",
      "湛",
      "暫",
      "佔",
      "站",
      "綻",
      "顫",
      "占",
      "戰",
      "蘸"
    ],
    "ㄆㄨˋ" : [
      "鋪",
      "暴",
      "曝",
      "瀑"
    ],
    "ㄐㄧㄣ" : [
      "巾",
      "金",
      "觔",
      "津",
      "襟",
      "筋",
      "斤",
      "今",
      "禁"
    ],
    "ㄕㄨㄚˇ" : [
      "耍"
    ],
    "ㄐㄧㄤ" : [
      "疆",
      "江",
      "薑",
      "韁",
      "僵",
      "將",
      "漿",
      "姜"
    ],
    "ㄘㄚ" : [
      "擦"
    ],
    "ㄑㄧㄢˊ" : [
      "前",
      "虔",
      "錢",
      "拑",
      "潛",
      "鉗",
      "乾"
    ],
    "ㄐㄧㄥ" : [
      "京",
      "精",
      "涇",
      "驚",
      "鯨",
      "兢",
      "菁",
      "睛",
      "荊",
      "經",
      "莖",
      "晶"
    ],
    "ㄈㄣˇ" : [
      "粉"
    ],
    "ㄌㄟˊ" : [
      "擂",
      "雷",
      "纍",
      "鐳"
    ],
    "ㄐㄩㄣˋ" : [
      "雋",
      "竣",
      "峻",
      "俊",
      "郡",
      "菌",
      "駿"
    ],
    "ㄨㄥˋ" : [
      "甕"
    ],
    "ㄑㄧㄢˋ" : [
      "歉",
      "縴",
      "芡",
      "倩",
      "塹",
      "欠"
    ],
    "ㄘㄞ" : [
      "猜"
    ],
    "ㄌㄟˋ" : [
      "淚",
      "累",
      "類"
    ],
    "ㄘㄤˊ" : [
      "藏"
    ],
    "ㄗㄨㄛˇ" : [
      "左",
      "佐"
    ],
    "ㄔㄨˇ" : [
      "杵",
      "處",
      "楚",
      "礎"
    ],
    "ㄘㄠ" : [
      "糙",
      "操"
    ],
    "ㄓㄨㄚ" : [
      "抓"
    ],
    "ㄍㄨㄟˋ" : [
      "跪",
      "桂",
      "櫃",
      "貴",
      "鱖",
      "匱"
    ],
    "ㄔˇ" : [
      "恥",
      "齒",
      "尺",
      "侈"
    ],
    "ㄈㄣˊ" : [
      "焚",
      "墳"
    ],
    "ㄘㄢ" : [
      "餐",
      "參"
    ],
    "ㄓㄨㄛ" : [
      "桌",
      "捉"
    ],
    "ㄎㄚˇ" : [
      "咯",
      "卡"
    ],
    "ㄘㄣ" : [
      "參"
    ],
    "ㄈㄣˋ" : [
      "糞",
      "份",
      "分",
      "憤",
      "忿",
      "奮"
    ],
    "ㄔㄨˊ" : [
      "鋤",
      "躇",
      "雛",
      "除",
      "儲",
      "櫥",
      "蜍",
      "廚"
    ],
    "ㄓㄨㄢˇ" : [
      "轉"
    ],
    "ㄔˊ" : [
      "遲",
      "持",
      "池",
      "弛",
      "匙",
      "馳"
    ],
    "ㄘㄤ" : [
      "滄",
      "蒼",
      "艙",
      "倉"
    ],
    "ㄆㄧㄢˊ" : [
      "胼",
      "便"
    ],
    "ㄍㄥˇ" : [
      "哽",
      "埂",
      "耿",
      "梗"
    ],
    "ㄔㄨˋ" : [
      "觸",
      "處",
      "怵",
      "矗",
      "畜"
    ],
    "ㄔˋ" : [
      "熾",
      "翅",
      "斥",
      "敕",
      "赤"
    ],
    "ㄓ" : [
      "汁",
      "肢",
      "胝",
      "脂",
      "織",
      "隻",
      "支",
      "知",
      "芝",
      "蜘",
      "之",
      "吱",
      "枝",
      "氏"
    ],
    "ㄔ" : [
      "嗤",
      "吃",
      "痴"
    ],
    "ㄕ" : [
      "師",
      "失",
      "詩",
      "施",
      "溼",
      "屍",
      "獅",
      "蝨",
      "濕"
    ],
    "ㄗ" : [
      "齊",
      "諮",
      "滋",
      "孜",
      "茲",
      "資",
      "姿"
    ],
    "ㄋㄩㄝˋ" : [
      "瘧",
      "虐",
      "謔"
    ],
    "ㄆㄧㄢˋ" : [
      "騙",
      "片"
    ],
    "ㄘ" : [
      "疵",
      "雌",
      "差"
    ],
    "ㄘㄨ" : [
      "粗"
    ],
    "ㄌㄨㄛˇ" : [
      "裸"
    ],
    "ㄙ" : [
      "撕",
      "私",
      "思",
      "斯",
      "絲",
      "司",
      "嘶",
      "鷥",
      "廝"
    ],
    "ㄖㄣˇ" : [
      "忍",
      "稔"
    ],
    "ㄗㄨㄛˊ" : [
      "作",
      "昨"
    ],
    "ㄓㄨㄟ" : [
      "椎",
      "追",
      "錐"
    ],
    "ㄚ" : [
      "阿",
      "啊"
    ],
    "ㄛ" : [
      "喔",
      "呵"
    ],
    "ㄜ" : [
      "阿"
    ],
    "ㄌㄧㄥˇ" : [
      "嶺",
      "領"
    ],
    "ㄓㄜˇ" : [
      "者"
    ],
    "ㄍㄥˋ" : [
      "更"
    ],
    "ㄞ" : [
      "挨",
      "唉",
      "哀",
      "埃",
      "哎"
    ],
    "ㄗㄨㄛˋ" : [
      "作",
      "做",
      "座",
      "坐"
    ],
    "ㄊㄞˊ" : [
      "臺",
      "檯",
      "苔",
      "台",
      "颱",
      "抬"
    ],
    "ㄠ" : [
      "凹"
    ],
    "ㄡ" : [
      "歐",
      "嘔",
      "謳",
      "鷗",
      "區"
    ],
    "ㄒㄧˇ" : [
      "洗",
      "喜",
      "徙"
    ],
    "ㄢ" : [
      "庵",
      "鞍",
      "諳",
      "安",
      "鵪"
    ],
    "ㄓㄨㄢ" : [
      "磚",
      "專"
    ],
    "ㄖㄣˊ" : [
      "人",
      "任",
      "壬",
      "仁"
    ],
    "ㄣ" : [
      "恩"
    ],
    "ㄊㄞˋ" : [
      "汰",
      "太",
      "態",
      "泰"
    ],
    "ㄤ" : [
      "骯"
    ],
    "ㄑㄧㄚ" : [
      "掐"
    ],
    "ㄖㄣˋ" : [
      "仞",
      "任",
      "刃",
      "認",
      "韌",
      "飪",
      "紉"
    ],
    "ㄏㄠˇ" : [
      "好",
      "郝"
    ],
    "ㄓㄨㄣ" : [
      "肫",
      "諄",
      "屯"
    ],
    "ㄓㄜˊ" : [
      "摺",
      "轍",
      "懾",
      "哲",
      "折",
      "輒",
      "褶"
    ],
    "ㄆㄢˊ" : [
      "胖",
      "般",
      "蟠",
      "盤"
    ],
    "ㄧ" : [
      "揖",
      "壹",
      "依",
      "一",
      "衣",
      "伊",
      "醫",
      "漪"
    ],
    "ㄓㄨㄢˋ" : [
      "撰",
      "轉",
      "傳",
      "賺"
    ],
    "ㄨㄟˇ" : [
      "偉",
      "瑋",
      "尾",
      "緯",
      "葦",
      "娓",
      "煒",
      "委"
    ],
    "ㄓㄨㄤ" : [
      "妝",
      "樁",
      "莊",
      "庄",
      "裝"
    ],
    "ㄨ" : [
      "污",
      "巫",
      "誣",
      "汙",
      "嗚",
      "烏",
      "屋",
      "惡"
    ],
    "ㄩ" : [
      "迂"
    ],
    "ㄓㄜˋ" : [
      "這",
      "蔗",
      "浙"
    ],
    "ㄆㄢˋ" : [
      "判",
      "叛",
      "盼",
      "畔",
      "拚"
    ],
    "ㄌㄨㄛˊ" : [
      "囉",
      "蘿",
      "羅",
      "儸",
      "騾",
      "籮",
      "鑼",
      "邏",
      "螺"
    ],
    "ㄒㄧˊ" : [
      "襲",
      "熄",
      "蓆",
      "惜",
      "席",
      "息",
      "媳",
      "昔",
      "錫",
      "習"
    ],
    "ㄓㄨㄥ" : [
      "鐘",
      "螽",
      "衷",
      "忠",
      "忪",
      "終",
      "鍾"
    ],
    "ㄙㄨㄥˇ" : [
      "聳",
      "悚",
      "慫"
    ],
    "ㄘㄞˇ" : [
      "踩",
      "採",
      "采",
      "睬",
      "彩",
      "綵"
    ],
    "ㄒㄧˋ" : [
      "系",
      "汐",
      "夕",
      "隙",
      "繫",
      "矽",
      "細",
      "係",
      "戲"
    ],
    "ㄌㄧㄥˊ" : [
      "聆",
      "齡",
      "零",
      "凌",
      "羚",
      "陵",
      "菱",
      "蛉",
      "鈴",
      "伶",
      "玲",
      "靈"
    ],
    "ㄏㄠˊ" : [
      "嚎",
      "號",
      "豪",
      "蠔",
      "毫"
    ],
    "ㄑㄧㄝ" : [
      "切"
    ],
    "ㄌㄨㄛˋ" : [
      "酪",
      "洛",
      "烙",
      "絡",
      "落",
      "駱"
    ],
    "ㄕㄨㄣˋ" : [
      "舜",
      "順",
      "瞬"
    ],
    "ㄨㄟˊ" : [
      "圍",
      "帷",
      "桅",
      "違",
      "薇",
      "嵬",
      "惟",
      "為",
      "唯",
      "巍",
      "微",
      "維",
      "危",
      "韋"
    ],
    "ㄏㄠˋ" : [
      "好",
      "號",
      "浩",
      "皓",
      "耗"
    ],
    "ㄋㄢ" : [
      "囡"
    ],
    "ㄌㄧㄥˋ" : [
      "另",
      "令"
    ],
    "ㄔㄢˇ" : [
      "闡",
      "剷",
      "諂",
      "產",
      "鏟"
    ],
    "ㄇㄨˇ" : [
      "姆",
      "牡",
      "畝",
      "拇",
      "母"
    ],
    "ㄨㄟˋ" : [
      "未",
      "蔚",
      "胃",
      "餵",
      "慰",
      "渭",
      "謂",
      "喂",
      "為",
      "遺",
      "尉",
      "偽",
      "位",
      "蝟",
      "衛",
      "味",
      "魏",
      "畏"
    ],
    "ㄘㄞˊ" : [
      "材",
      "財",
      "裁",
      "才"
    ],
    "ㄋㄤˊ" : [
      "囊"
    ],
    "ㄑㄧㄠ" : [
      "蹺",
      "敲"
    ],
    "ㄘㄞˋ" : [
      "菜",
      "蔡"
    ],
    "ㄟˋ" : [
      "欸"
    ],
    "ㄑㄧㄡ" : [
      "蚯",
      "鰍",
      "龜",
      "秋",
      "丘",
      "邱"
    ],
    "ㄊㄨㄣˊ" : [
      "臀",
      "屯",
      "豚"
    ],
    "ㄎㄨㄥˇ" : [
      "恐",
      "孔"
    ],
    "ㄔㄢˊ" : [
      "單",
      "饞",
      "蟾",
      "蟬",
      "潺",
      "纏",
      "禪"
    ],
    "ㄑㄧㄢ" : [
      "遷",
      "仟",
      "嵌",
      "騫",
      "謙",
      "阡",
      "鉛",
      "簽",
      "千",
      "牽",
      "籤"
    ],
    "ㄩㄥˇ" : [
      "踴",
      "擁",
      "詠",
      "恿",
      "蛹",
      "湧",
      "勇",
      "俑",
      "泳",
      "永"
    ],
    "ㄍㄟˇ" : [
      "給"
    ],
    "ㄑㄧㄣ" : [
      "親",
      "侵",
      "欽"
    ],
    "ㄇㄨˋ" : [
      "木",
      "慕",
      "墓",
      "睦",
      "穆",
      "暮",
      "沐",
      "目",
      "牧",
      "幕",
      "募"
    ],
    "ㄊㄨㄣˋ" : [
      "褪"
    ],
    "ㄋㄧㄡˇ" : [
      "鈕",
      "紐",
      "扭"
    ],
    "ㄙㄨㄥˋ" : [
      "送",
      "訟",
      "誦",
      "宋",
      "頌"
    ],
    "ㄑㄧㄤ" : [
      "搶",
      "腔",
      "羌",
      "鏘",
      "鎗",
      "槍"
    ],
    "ㄙㄤˇ" : [
      "嗓"
    ],
    "ㄑㄧㄥ" : [
      "清",
      "蜻",
      "傾",
      "青",
      "輕",
      "卿",
      "氫"
    ],
    "ㄕㄨˇ" : [
      "糬",
      "署",
      "藷",
      "鼠",
      "屬",
      "蜀",
      "數",
      "薯",
      "暑",
      "黍"
    ],
    "ㄩㄥˋ" : [
      "佣",
      "用"
    ],
    "ㄒㄩㄝˇ" : [
      "雪"
    ],
    "ㄉㄧㄠˋ" : [
      "掉",
      "調",
      "弔",
      "吊",
      "釣"
    ],
    "ㄔㄨㄟˊ" : [
      "搥",
      "槌",
      "垂",
      "鎚",
      "錘"
    ],
    "ㄙㄤˋ" : [
      "喪"
    ],
    "ㄅㄧˇ" : [
      "妣",
      "鄙",
      "筆",
      "彼",
      "比"
    ],
    "ㄔㄨㄛ" : [
      "戳"
    ],
    "ㄏㄚˇ" : [
      "哈"
    ],
    "ㄎㄨㄥˋ" : [
      "控",
      "空"
    ],
    "ㄋㄧㄡˊ" : [
      "牛"
    ],
    "ㄕㄨˊ" : [
      "淑",
      "塾",
      "孰",
      "贖",
      "叔"
    ],
    "ㄕㄨˋ" : [
      "束",
      "署",
      "曙",
      "恕",
      "述",
      "樹",
      "數",
      "豎",
      "倏",
      "術",
      "漱",
      "庶",
      "墅"
    ],
    "ㄅㄧˊ" : [
      "鼻"
    ],
    "ㄧㄤˇ" : [
      "仰",
      "癢",
      "養",
      "氧"
    ],
    "ㄋㄞˇ" : [
      "奶",
      "迺",
      "乃"
    ],
    "ㄅㄧˋ" : [
      "避",
      "閉",
      "碧",
      "祕",
      "壁",
      "璧",
      "嗶",
      "陛",
      "敝",
      "蔽",
      "臂",
      "必",
      "斃",
      "弊",
      "婢",
      "畢",
      "秘",
      "庇",
      "比",
      "幣",
      "痺"
    ],
    "ㄏㄚˊ" : [
      "蛤",
      "蝦"
    ],
    "ㄒㄩㄝˊ" : [
      "學"
    ],
    "ㄐㄩㄥˇ" : [
      "迥",
      "炯",
      "窘"
    ],
    "ㄔㄨㄟ" : [
      "炊",
      "吹"
    ],
    "ㄗㄣˇ" : [
      "怎"
    ],
    "ㄑㄧㄤˇ" : [
      "襁",
      "搶",
      "強"
    ],
    "ㄖㄥ" : [
      "扔"
    ],
    "ㄔㄜˇ" : [
      "扯"
    ],
    "ㄇㄢˇ" : [
      "滿"
    ],
    "ㄒㄩㄝˋ" : [
      "穴",
      "削"
    ],
    "ㄧㄤˊ" : [
      "揚",
      "洋",
      "羊",
      "陽",
      "烊",
      "徉",
      "楊",
      "瘍"
    ],
    "ㄉㄨㄟˋ" : [
      "隊",
      "對",
      "兌"
    ],
    "ㄧㄤˋ" : [
      "樣",
      "養",
      "漾"
    ],
    "ㄋㄞˋ" : [
      "奈",
      "耐"
    ],
    "ㄔㄨㄢ" : [
      "川",
      "穿"
    ],
    "ㄊㄧㄝˇ" : [
      "帖",
      "鐵"
    ],
    "ㄒㄧㄚ" : [
      "蝦",
      "瞎"
    ],
    "ㄔㄨㄣ" : [
      "春"
    ],
    "ㄏㄨㄢˇ" : [
      "緩"
    ],
    "ㄇㄢˊ" : [
      "饅",
      "蔓",
      "鰻",
      "蠻",
      "蹣",
      "瞞",
      "埋"
    ],
    "ㄔㄨㄤ" : [
      "囪",
      "創",
      "瘡",
      "窗"
    ],
    "ㄔㄜˋ" : [
      "掣",
      "轍",
      "撤",
      "徹",
      "澈",
      "坼"
    ],
    "ㄇㄢˋ" : [
      "蔓",
      "慢",
      "曼",
      "漫",
      "幔"
    ],
    "ㄑㄧㄤˊ" : [
      "牆",
      "薔",
      "強",
      "戕"
    ],
    "ㄔㄨㄥ" : [
      "舂",
      "充",
      "憧",
      "忡",
      "衝",
      "沖"
    ],
    "ㄌㄤˇ" : [
      "朗"
    ],
    "ㄒㄧㄝ" : [
      "些",
      "歇",
      "楔"
    ],
    "ㄉㄚ" : [
      "搭",
      "答"
    ],
    "ㄓㄨㄛˊ" : [
      "酌",
      "擢",
      "琢",
      "灼",
      "浞",
      "鐲",
      "啄",
      "茁",
      "濯",
      "濁",
      "卓",
      "拙",
      "著"
    ],
    "ㄑㄧㄤˋ" : [
      "嗆"
    ],
    "ㄕㄢˇ" : [
      "陝",
      "閃"
    ],
    "ㄈㄨˇ" : [
      "撫",
      "斧",
      "脯",
      "腐",
      "俯",
      "輔",
      "府",
      "甫"
    ],
    "ㄉㄞ" : [
      "待",
      "呆"
    ],
    "ㄌㄤˊ" : [
      "螂",
      "瑯",
      "琅",
      "榔",
      "郎",
      "蜋",
      "廊",
      "狼"
    ],
    "ㄒㄧㄠ" : [
      "囂",
      "消",
      "驍",
      "瀟",
      "蕭",
      "宵",
      "逍",
      "哮",
      "削",
      "霄",
      "銷",
      "簫",
      "硝"
    ],
    "ㄏㄨㄢˊ" : [
      "桓",
      "環",
      "寰",
      "鬟",
      "嬛",
      "還"
    ],
    "ㄙㄞˋ" : [
      "塞",
      "賽"
    ],
    "ㄉㄠ" : [
      "刀",
      "叨"
    ],
    "ㄌㄤˋ" : [
      "浪"
    ],
    "ㄒㄧㄡ" : [
      "饈",
      "脩",
      "羞",
      "休",
      "咻",
      "修"
    ],
    "ㄉㄡ" : [
      "兜",
      "都"
    ],
    "ㄉㄢ" : [
      "擔",
      "單",
      "眈",
      "殫",
      "丹",
      "耽"
    ],
    "ㄏㄨㄢˋ" : [
      "奐",
      "換",
      "患",
      "喚",
      "渙",
      "瘓",
      "幻",
      "煥"
    ],
    "ㄈㄨˊ" : [
      "服",
      "夫",
      "拂",
      "輻",
      "浮",
      "符",
      "縛",
      "芙",
      "芾",
      "蝠",
      "伏",
      "苻",
      "彿",
      "佛",
      "俘",
      "弗",
      "袱",
      "匐",
      "福",
      "扶",
      "幅"
    ],
    "ㄒㄧㄢ" : [
      "掀",
      "先",
      "鮮",
      "仙",
      "纖"
    ],
    "ㄐㄧㄠˇ" : [
      "餃",
      "角",
      "腳",
      "繳",
      "僥",
      "攪",
      "矯",
      "絞",
      "皎",
      "狡"
    ],
    "ㄉㄤ" : [
      "噹",
      "當",
      "鐺"
    ],
    "ㄕㄢˋ" : [
      "訕",
      "擅",
      "繕",
      "單",
      "善",
      "禪",
      "扇"
    ],
    "ㄈㄨˋ" : [
      "付",
      "覆",
      "複",
      "腹",
      "附",
      "富",
      "復",
      "傅",
      "副",
      "負",
      "咐",
      "賦",
      "父",
      "駙",
      "赴",
      "婦",
      "馥"
    ],
    "ㄒㄧㄣ" : [
      "薪",
      "新",
      "辛",
      "心",
      "馨",
      "欣"
    ],
    "ㄉㄥ" : [
      "燈",
      "登"
    ],
    "˙ㄈㄣ" : [
      "噴"
    ],
    "ㄒㄧㄤ" : [
      "襄",
      "鄉",
      "鑲",
      "湘",
      "相",
      "廂",
      "香",
      "箱"
    ],
    "ㄉㄧ" : [
      "低",
      "滴"
    ],
    "ㄉㄨ" : [
      "嘟",
      "督",
      "都"
    ],
    "ㄒㄧㄥ" : [
      "興",
      "腥",
      "惺",
      "猩",
      "星"
    ],
    "ㄑㄩㄢˇ" : [
      "犬"
    ],
    "ㄒㄧㄡˇ" : [
      "朽",
      "宿"
    ],
    "ㄖㄨˇ" : [
      "汝",
      "乳"
    ],
    "ㄧㄞˊ" : [
      "崖"
    ],
    "ㄕㄨㄚ" : [
      "刷"
    ],
    "ㄅㄧㄠˇ" : [
      "錶",
      "表"
    ],
    "ㄐㄧㄠˊ" : [
      "嚼"
    ],
    "ㄓㄨㄤˋ" : [
      "壯",
      "撞",
      "僮",
      "狀"
    ],
    "ㄓㄡˇ" : [
      "肘"
    ],
    "ㄆㄧˇ" : [
      "圮",
      "否",
      "匹"
    ],
    "ㄕㄨㄛ" : [
      "說"
    ],
    "ㄊㄨㄥˇ" : [
      "桶",
      "筒",
      "統"
    ],
    "ㄖㄨˊ" : [
      "如",
      "嚅",
      "儒",
      "孺",
      "茹",
      "蠕"
    ],
    "ㄐㄧㄠˋ" : [
      "覺",
      "校",
      "較",
      "轎",
      "教",
      "叫",
      "窖"
    ],
    "ㄖㄨˋ" : [
      "入",
      "辱",
      "褥"
    ],
    "ㄑㄩㄢˊ" : [
      "詮",
      "蜷",
      "全",
      "銓",
      "權",
      "卷",
      "拳",
      "泉",
      "痊"
    ],
    "ㄔㄚ" : [
      "插",
      "差",
      "叉"
    ],
    "ㄓㄡˊ" : [
      "軸"
    ],
    "ㄆㄧˊ" : [
      "疲",
      "啤",
      "琵",
      "脾",
      "皮",
      "枇"
    ],
    "ㄨㄤˇ" : [
      "惘",
      "往",
      "網",
      "枉"
    ],
    "ㄔㄜ" : [
      "車"
    ],
    "ㄕㄨㄞ" : [
      "摔",
      "衰"
    ],
    "ㄆㄧˋ" : [
      "闢",
      "僻",
      "譬",
      "屁",
      "媲"
    ],
    "ㄓㄡˋ" : [
      "縐",
      "冑",
      "宙",
      "紂",
      "咒",
      "晝",
      "皺"
    ],
    "ㄑㄩㄢˋ" : [
      "券",
      "勸"
    ],
    "ㄔㄞ" : [
      "差",
      "拆"
    ],
    "ㄋㄩˇ" : [
      "女"
    ],
    "ㄒㄧㄡˋ" : [
      "琇",
      "嗅",
      "繡",
      "臭",
      "宿",
      "鏽",
      "秀",
      "袖"
    ],
    "ㄏㄥˊ" : [
      "恆",
      "橫",
      "衡"
    ],
    "ㄔㄠ" : [
      "鈔",
      "抄",
      "超"
    ],
    "ㄕㄜˇ" : [
      "捨",
      "舍"
    ],
    "ㄎㄨㄞˋ" : [
      "會",
      "筷",
      "塊",
      "膾",
      "檜",
      "快"
    ],
    "ㄈㄢˇ" : [
      "返",
      "反"
    ],
    "ㄏㄥˋ" : [
      "橫"
    ],
    "ㄉㄧㄢˇ" : [
      "碘",
      "典",
      "點"
    ],
    "ㄌㄞˊ" : [
      "來",
      "萊"
    ],
    "ㄨㄤˊ" : [
      "亡",
      "王"
    ],
    "ㄊㄨㄥˊ" : [
      "仝",
      "桐",
      "銅",
      "僮",
      "茼",
      "彤",
      "童",
      "同"
    ],
    "ㄨˇ" : [
      "午",
      "武",
      "五",
      "摀",
      "伍",
      "侮",
      "鵡",
      "舞"
    ],
    "ㄔㄡ" : [
      "抽"
    ],
    "ㄅㄧㄠ" : [
      "飆",
      "彪",
      "標",
      "鑣"
    ],
    "ㄨㄤˋ" : [
      "妄",
      "望",
      "旺",
      "忘",
      "王"
    ],
    "ㄔㄢ" : [
      "攙",
      "摻"
    ],
    "ㄅㄛˇ" : [
      "跛",
      "簸"
    ],
    "ㄌㄞˋ" : [
      "籟",
      "賴",
      "睞",
      "癩"
    ],
    "ㄕㄨㄢ" : [
      "拴",
      "栓"
    ],
    "ㄔㄣ" : [
      "瞋"
    ],
    "ㄔㄤ" : [
      "猖",
      "倡",
      "昌",
      "菖"
    ],
    "ㄘㄣˊ" : [
      "涔"
    ],
    "ㄔㄥ" : [
      "撐",
      "瞠",
      "鎗",
      "稱",
      "鐺"
    ],
    "ㄨˊ" : [
      "蕪",
      "無",
      "蜈",
      "唔",
      "梧",
      "吾",
      "吳",
      "毋"
    ],
    "ㄊㄨㄥˋ" : [
      "痛"
    ],
    "ㄕㄜˊ" : [
      "舌",
      "蛇",
      "折"
    ],
    "ㄈㄢˊ" : [
      "藩",
      "帆",
      "樊",
      "凡",
      "繁",
      "蕃",
      "煩"
    ],
    "ㄨˋ" : [
      "悟",
      "塢",
      "兀",
      "寤",
      "誤",
      "務",
      "霧",
      "婺",
      "物",
      "晤",
      "戊",
      "勿",
      "惡"
    ],
    "ㄅㄧㄢ" : [
      "邊",
      "鞭",
      "蝙",
      "編"
    ],
    "ㄕㄨㄤ" : [
      "雙",
      "霜"
    ],
    "ㄑㄧㄝˇ" : [
      "且"
    ],
    "ㄕㄜˋ" : [
      "涉",
      "設",
      "攝",
      "舍",
      "射",
      "社",
      "赦"
    ],
    "ㄈㄢˋ" : [
      "犯",
      "範",
      "飯",
      "范",
      "販",
      "泛",
      "梵",
      "氾"
    ],
    "ㄅㄧㄣ" : [
      "瀕",
      "濱",
      "繽",
      "檳",
      "彬",
      "賓"
    ],
    "ㄔㄨ" : [
      "出",
      "齣",
      "初"
    ],
    "ㄅㄛˊ" : [
      "柏",
      "蔔",
      "脖",
      "搏",
      "薄",
      "渤",
      "泊",
      "帛",
      "膊",
      "箔",
      "伯",
      "礴",
      "博",
      "駁",
      "勃"
    ],
    "ㄇㄧㄡˋ" : [
      "繆",
      "謬"
    ],
    "ㄍㄨㄚˇ" : [
      "寡"
    ],
    "ㄖㄨㄢˇ" : [
      "阮",
      "軟"
    ],
    "ㄍㄤˇ" : [
      "崗",
      "港"
    ],
    "ㄅㄛˋ" : [
      "播",
      "薄",
      "簸"
    ],
    "ㄅㄧㄥ" : [
      "冰",
      "兵"
    ],
    "˙ㄓㄜ" : [
      "著"
    ],
    "ㄉㄧㄢˋ" : [
      "踮",
      "奠",
      "電",
      "惦",
      "靛",
      "佃",
      "玷",
      "殿",
      "店",
      "墊",
      "甸",
      "澱"
    ],
    "ㄉㄨˇ" : [
      "肚",
      "篤",
      "睹",
      "堵",
      "賭"
    ],
    "ㄖㄢˇ" : [
      "染",
      "冉"
    ],
    "ㄏㄨㄛˇ" : [
      "夥",
      "火",
      "伙"
    ],
    "ㄘㄨㄣˇ" : [
      "忖"
    ],
    "ㄋㄧㄣˊ" : [
      "您"
    ],
    "ㄇㄚ" : [
      "嬤",
      "媽"
    ],
    "ㄆㄡˇ" : [
      "剖"
    ],
    "ㄍㄤˋ" : [
      "槓"
    ],
    "ㄆㄧㄝˇ" : [
      "撇"
    ],
    "ㄑㄧㄝˊ" : [
      "伽",
      "茄"
    ],
    "ㄇㄛ" : [
      "摸"
    ],
    "ㄋㄨㄢˇ" : [
      "暖"
    ],
    "ㄉㄨˊ" : [
      "犢",
      "毒",
      "獨",
      "頓",
      "瀆",
      "讀"
    ],
    "ㄖㄢˊ" : [
      "燃",
      "然"
    ],
    "ㄑㄧㄝˋ" : [
      "妾",
      "切",
      "愜",
      "鍥",
      "竊"
    ],
    "ㄉㄨˋ" : [
      "妒",
      "肚",
      "杜",
      "渡",
      "鍍",
      "度"
    ],
    "ㄇㄠ" : [
      "貓"
    ],
    "ㄍㄨㄚˋ" : [
      "掛",
      "褂",
      "卦"
    ],
    "ㄍㄨㄣˇ" : [
      "滾"
    ],
    "ㄘㄨㄣˊ" : [
      "存"
    ],
    "ㄏㄨㄛˊ" : [
      "活"
    ],
    "ㄇㄣ" : [
      "悶"
    ],
    "ㄇㄥ" : [
      "矇"
    ],
    "ㄗㄨˇ" : [
      "組",
      "阻",
      "祖",
      "俎"
    ],
    "ㄛˊ" : [
      "哦"
    ],
    "ㄏㄨㄛˋ" : [
      "壑",
      "惑",
      "獲",
      "霍",
      "禍",
      "穫",
      "貨",
      "和",
      "豁",
      "或"
    ],
    "ㄘㄨㄣˋ" : [
      "寸"
    ],
    "ㄇㄧ" : [
      "咪",
      "瞇"
    ],
    "ㄔㄡˇ" : [
      "醜",
      "丑"
    ],
    "ㄇㄧˇ" : [
      "米",
      "靡"
    ],
    "ㄨㄞˋ" : [
      "外"
    ],
    "ㄏㄨㄤˇ" : [
      "恍",
      "謊",
      "晃"
    ],
    "ㄕㄨㄞˇ" : [
      "甩"
    ],
    "ㄋㄣˋ" : [
      "嫩"
    ],
    "ㄗㄨˊ" : [
      "卒",
      "族",
      "足"
    ],
    "ㄌㄧㄠˇ" : [
      "了",
      "瞭"
    ],
    "ㄔㄡˊ" : [
      "酬",
      "仇",
      "躊",
      "惆",
      "愁",
      "稠",
      "籌",
      "綢",
      "疇"
    ],
    "ㄇㄧˊ" : [
      "麋",
      "糜",
      "瀰",
      "謎",
      "迷",
      "獼",
      "靡",
      "彌"
    ],
    "ㄍㄞˇ" : [
      "改"
    ],
    "ㄗㄨㄟˇ" : [
      "嘴"
    ],
    "ㄔㄡˋ" : [
      "臭"
    ],
    "ㄇㄧˋ" : [
      "祕",
      "謐",
      "密",
      "蜜",
      "覓",
      "秘",
      "泌"
    ],
    "ㄆㄧㄝ" : [
      "撇",
      "瞥"
    ],
    "ㄍㄨㄣˋ" : [
      "棍"
    ],
    "ㄌㄩˇ" : [
      "鋁",
      "屢",
      "履",
      "旅",
      "縷",
      "侶",
      "呂"
    ],
    "ㄏㄨㄤˊ" : [
      "磺",
      "凰",
      "惶",
      "徨",
      "簧",
      "潢",
      "皇",
      "黃",
      "煌"
    ],
    "ㄖㄜˇ" : [
      "惹",
      "若"
    ],
    "ㄉㄢˇ" : [
      "膽",
      "撢"
    ],
    "ㄆㄧㄠ" : [
      "漂",
      "飄"
    ],
    "ㄌㄧㄠˊ" : [
      "聊",
      "撩",
      "燎",
      "療",
      "嘹",
      "遼",
      "繚",
      "寥",
      "僚",
      "潦",
      "寮"
    ],
    "ㄏㄨㄤˋ" : [
      "晃"
    ],
    "ㄆㄛˇ" : [
      "頗"
    ],
    "ㄌㄩˊ" : [
      "櫚",
      "驢"
    ],
    "ㄍㄞˋ" : [
      "蓋",
      "溉",
      "概",
      "丐"
    ],
    "ㄒㄧㄚˊ" : [
      "黠",
      "遐",
      "瑕",
      "挾",
      "峽",
      "轄",
      "匣",
      "暇",
      "霞",
      "俠",
      "狹"
    ],
    "ㄕㄨㄞˋ" : [
      "蟀",
      "帥",
      "率"
    ],
    "ㄐㄧㄢˇ" : [
      "撿",
      "檢",
      "鹼",
      "揀",
      "儉",
      "繭",
      "減",
      "瞼",
      "剪",
      "簡",
      "翦"
    ],
    "ㄌㄩˋ" : [
      "壘",
      "律",
      "慮",
      "濾",
      "率",
      "綠",
      "氯"
    ],
    "ㄆㄧㄢ" : [
      "翩",
      "篇",
      "偏",
      "扁"
    ],
    "ㄌㄧㄠˋ" : [
      "瞭",
      "料",
      "廖"
    ],
    "ㄒㄧㄚˋ" : [
      "嚇",
      "廈",
      "下"
    ],
    "ㄖㄜˋ" : [
      "熱"
    ],
    "ㄉㄢˋ" : [
      "淡",
      "擔",
      "誕",
      "旦",
      "蛋",
      "憚",
      "石",
      "彈",
      "但",
      "澹"
    ],
    "ㄆㄧㄣ" : [
      "拼"
    ],
    "ㄦˇ" : [
      "餌",
      "爾",
      "耳",
      "邇"
    ],
    "ㄆㄛˊ" : [
      "婆"
    ],
    "ㄗㄨㄟˋ" : [
      "最",
      "醉",
      "罪"
    ],
    "ㄆㄛˋ" : [
      "粕",
      "破",
      "魄",
      "珀",
      "迫"
    ],
    "ㄦˊ" : [
      "兒",
      "而"
    ],
    "ㄧㄣˇ" : [
      "蚓",
      "尹",
      "飲",
      "癮",
      "引",
      "隱"
    ],
    "ㄆㄧㄥ" : [
      "乒"
    ],
    "ㄦˋ" : [
      "二",
      "貳"
    ],
    "ㄒㄧ" : [
      "窸",
      "釐",
      "犧",
      "犀",
      "羲",
      "奚",
      "淅",
      "攜",
      "曦",
      "熙",
      "熹",
      "西",
      "悉",
      "嘻",
      "希",
      "溪",
      "烯",
      "膝",
      "蜥",
      "蟋",
      "谿",
      "嬉",
      "稀",
      "禧",
      "兮",
      "蠵",
      "吸",
      "晰",
      "析"
    ],
    "ㄅㄧㄢˇ" : [
      "貶",
      "匾",
      "扁"
    ],
    "ㄊㄨˇ" : [
      "土",
      "吐"
    ],
    "ㄒㄩ" : [
      "虛",
      "噓",
      "鬚",
      "需",
      "吁",
      "須",
      "戌",
      "墟"
    ],
    "ㄎㄤˊ" : [
      "扛"
    ],
    "ㄇㄡˇ" : [
      "某"
    ],
    "ㄧㄣˊ" : [
      "齦",
      "淫",
      "寅",
      "霪",
      "銀",
      "吟",
      "垠"
    ],
    "ㄎㄤˋ" : [
      "亢",
      "炕",
      "抗"
    ],
    "ㄐㄧㄢˋ" : [
      "劍",
      "見",
      "踐",
      "間",
      "賤",
      "艦",
      "箭",
      "檻",
      "件",
      "薦",
      "澗",
      "荐",
      "濺",
      "諫",
      "鍵",
      "監",
      "漸",
      "建",
      "健",
      "餞",
      "毽",
      "鑑"
    ],
    "ㄉㄨㄛ" : [
      "多"
    ],
    "ㄧㄣˋ" : [
      "蔭",
      "飲",
      "印"
    ],
    "ㄗㄢˊ" : [
      "咱"
    ],
    "ㄊㄨˊ" : [
      "圖",
      "涂",
      "途",
      "塗",
      "屠",
      "徒",
      "荼",
      "突",
      "凸"
    ],
    "ㄇㄧㄣˇ" : [
      "憫",
      "敏",
      "皿"
    ],
    "ㄗㄢˋ" : [
      "讚",
      "贊"
    ],
    "ㄊㄨˋ" : [
      "兔",
      "吐",
      "菟"
    ],
    "˙ㄇㄚ" : [
      "嘛",
      "嗎"
    ],
    "ㄅㄚ" : [
      "疤",
      "粑",
      "巴",
      "捌",
      "笆",
      "峇",
      "八",
      "芭",
      "叭",
      "吧",
      "扒"
    ],
    "ㄇㄡˊ" : [
      "繆",
      "謀",
      "哞",
      "牟"
    ],
    "ㄅㄛ" : [
      "剝",
      "缽",
      "般",
      "撥",
      "玻",
      "波",
      "菠"
    ],
    "ㄒㄧㄣˋ" : [
      "信"
    ],
    "ㄉㄨㄟ" : [
      "堆"
    ],
    "˙ㄇㄜ" : [
      "麼"
    ],
    "ㄅㄟ" : [
      "杯",
      "背",
      "碑",
      "悲",
      "盃",
      "卑"
    ]
  }
}